<?xml version="1.0" encoding="utf-8"?>
<document id="6263127">
  <s id="1">
    <time id="T1S" value="00:00:00,548" />
    <w id="1.1">Star</w>
    <w id="1.2">Wars</w>
    <w id="1.3">:</w>
  </s>
  <s id="2">
    <w id="2.1">The</w>
    <w id="2.2">Clone</w>
    <w id="2.3">Wars</w>
    <w id="2.4">S06E05</w>
    <w id="2.5">-</w>
    <w id="2.6">"</w>
    <w id="2.7">An</w>
    <w id="2.8">Old</w>
    <w id="2.9">Friend</w>
    <w id="2.10">"</w>
    <time id="T1E" value="00:00:07,500" />
  </s>
  <s id="3">
    <time id="T2S" value="00:00:09,912" />
    <w alternative="Amar" id="3.1">AMAR</w>
    <w id="3.2">,</w>
    <w alternative="é" id="3.3">É</w>
    <w alternative="confiar" id="3.4">CONFIAR</w>
    <w id="3.5">.</w>
  </s>
  <s id="4">
    <w alternative="Confiar" id="4.1">CONFIAR</w>
    <w alternative="é" id="4.2">É</w>
    <w alternative="acreditar" id="4.3">ACREDITAR</w>
    <w id="4.4">.</w>
    <time id="T2E" value="00:00:14,512" />
  </s>
  <s id="5">
    <time id="T3S" value="00:00:16,613" />
    <w id="5.1">Como</w>
    <w id="5.2">a</w>
    <w id="5.3">guerra</w>
    <w id="5.4">entre</w>
    <w id="5.5">a</w>
    <w id="5.6">República</w>
    <w id="5.7">e</w>
    <w id="5.8">os</w>
    <w id="5.9">Separatistas</w>
    <w id="5.10">aumenta</w>
    <w id="5.11">...</w>
    <time id="T3E" value="00:00:19,966" />
    <time id="T4S" value="00:00:20,000" />
    <w id="5.12">muitos</w>
    <w id="5.13">são</w>
    <w id="5.14">expulsos</w>
    <w id="5.15">dos</w>
    <w id="5.16">seus</w>
    <w id="5.17">planetas</w>
    <w id="5.18">natais</w>
    <w id="5.19">,</w>
    <time id="T4E" value="00:00:22,370" />
    <time id="T5S" value="00:00:22,377" />
    <w id="5.20">e</w>
    <w id="5.21">cabe</w>
    <w id="5.22">à</w>
    <w id="5.23">Senadora</w>
    <w id="5.24">Amidala</w>
    <w id="5.25">garantir-lhes</w>
    <w id="5.26">ajuda</w>
    <w id="5.27">.</w>
    <time id="T5E" value="00:00:26,372" />
  </s>
  <s id="6">
    <time id="T6S" value="00:00:26,373" />
    <w id="6.1">Toda</w>
    <w id="6.2">a</w>
    <w id="6.3">atenção</w>
    <w id="6.4">se</w>
    <w id="6.5">volta</w>
    <w id="6.6">para</w>
    <w id="6.7">o</w>
    <w id="6.8">Clã</w>
    <w id="6.9">Bancário</w>
    <w id="6.10">...</w>
    <time id="T6E" value="00:00:28,749" />
    <time id="T7S" value="00:00:28,750" />
    <w id="6.11">e</w>
    <w id="6.12">o</w>
    <w id="6.13">planeta</w>
    <w id="6.14">Scipio</w>
    <w id="6.15">.</w>
  </s>
  <s id="7">
    <w id="7.1">Num</w>
    <w id="7.2">esforço</w>
    <w id="7.3">para</w>
    <w id="7.4">ficar</w>
    <w id="7.5">...</w>
    <time id="T7E" value="00:00:31,402" />
    <time id="T8S" value="00:00:31,563" />
    <w id="7.6">independente</w>
    <w id="7.7">da</w>
    <w id="7.8">República</w>
    <w id="7.9">e</w>
    <w id="7.10">dos</w>
    <w id="7.11">Separatistas</w>
    <w id="7.12">,</w>
    <time id="T8E" value="00:00:34,264" />
    <time id="T9S" value="00:00:34,265" />
    <w id="7.13">todas</w>
    <w id="7.14">as</w>
    <w id="7.15">operações</w>
    <w id="7.16">são</w>
    <w id="7.17">divididas</w>
    <w id="7.18">...</w>
    <time id="T9E" value="00:00:36,082" />
    <time id="T10S" value="00:00:36,083" />
    <w id="7.19">e</w>
    <w id="7.20">as</w>
    <w id="7.21">transacções</w>
    <w id="7.22">com</w>
    <w id="7.23">dinheiro</w>
    <w id="7.24">realizadas</w>
    <w id="7.25">na</w>
    <w id="7.26">Zona</w>
    <w id="7.27">Neutra</w>
    <w id="7.28">,</w>
    <time id="T10E" value="00:00:38,777" />
    <time id="T11S" value="00:00:38,778" />
    <w id="7.29">nas</w>
    <w id="7.30">proximidades</w>
    <w id="7.31">do</w>
    <w id="7.32">cofre</w>
    <w id="7.33">principal</w>
    <w id="7.34">.</w>
    <time id="T11E" value="00:00:40,862" />
  </s>
  <s id="8">
    <time id="T12S" value="00:00:40,863" />
    <w id="8.1">Para</w>
    <w id="8.2">as</w>
    <w id="8.3">operações</w>
    <w id="8.4">continuarem</w>
    <w id="8.5">...</w>
    <time id="T12E" value="00:00:42,655" />
    <time id="T13S" value="00:00:42,656" />
    <w id="8.6">não</w>
    <w id="8.7">deve</w>
    <w id="8.8">haver</w>
    <w id="8.9">guerra</w>
    <w id="8.10">em</w>
    <w id="8.11">Scipio</w>
    <w id="8.12">.</w>
    <time id="T13E" value="00:00:45,283" />
  </s>
  <s id="9">
    <time id="T14S" value="00:00:45,284" />
    <w id="9.1">No</w>
    <w id="9.2">entanto</w>
    <w id="9.3">,</w>
    <w id="9.4">um</w>
    <w id="9.5">preocupação</w>
    <w id="9.6">com</w>
    <w id="9.7">a</w>
    <w id="9.8">estabilidade</w>
    <w id="9.9">do</w>
    <w id="9.10">Clã</w>
    <w id="9.11">Bancário</w>
    <w id="9.12">,</w>
    <time id="T14E" value="00:00:48,277" />
    <time id="T15S" value="00:00:48,278" />
    <w id="9.13">tem-se</w>
    <w id="9.14">formado</w>
    <w id="9.15">dentro</w>
    <w id="9.16">da</w>
    <w id="9.17">República</w>
    <w id="9.18">,</w>
    <time id="T15E" value="00:00:50,221" />
    <time id="T16S" value="00:00:50,222" />
    <w id="9.19">uma</w>
    <w id="9.20">vez</w>
    <w id="9.21">que</w>
    <w id="9.22">a</w>
    <w id="9.23">fonte</w>
    <w id="9.24">de</w>
    <w id="9.25">dinheiro</w>
    <w id="9.26">pode</w>
    <w id="9.27">estar</w>
    <w id="9.28">em</w>
    <w id="9.29">perigo</w>
    <w id="9.30">!</w>
    <time id="T16E" value="00:00:53,634" />
  </s>
  <s id="10">
    <time id="T17S" value="00:00:56,253" />
    <w id="10.1">Bem-vinda</w>
    <w id="10.2">à</w>
    <w id="10.3">Scipio</w>
    <w id="10.4">,</w>
    <w id="10.5">Senadora</w>
    <w id="10.6">.</w>
    <time id="T17E" value="00:00:58,671" />
  </s>
  <s id="11">
    <time id="T18S" value="00:00:58,672" />
    <w id="11.1">Se</w>
    <w id="11.2">a</w>
    <w id="11.3">senhora</w>
    <w id="11.4">me</w>
    <w id="11.5">seguir</w>
    <w id="11.6">...</w>
    <time id="T18E" value="00:01:00,339" />
    <time id="T19S" value="00:01:00,340" />
    <w id="11.7">vamos</w>
    <w id="11.8">viajar</w>
    <w id="11.9">até</w>
    <w id="11.10">à</w>
    <w id="11.11">Zona</w>
    <w id="11.12">Neutra</w>
    <w id="11.13">.</w>
    <time id="T19E" value="00:01:04,136" />
  </s>
  <s id="12">
    <time id="T20S" value="00:01:11,852" />
    <w id="12.1">Va-tee</w>
    <w id="12.2">,</w>
    <w id="12.3">p</w>
    <w id="12.4">'</w>
    <w id="12.5">tee</w>
    <w id="12.6">see-li</w>
    <w id="12.7">Senatee</w>
    <w id="12.8">Amidala</w>
    <w id="12.9">.</w>
    <time id="T20E" value="00:01:15,739" />
  </s>
  <s id="13">
    <time id="T21S" value="00:01:20,269" />
    <w id="13.1">Receio</w>
    <w id="13.2">que</w>
    <w id="13.3">os</w>
    <w id="13.4">seus</w>
    <w id="13.5">"</w>
    <w id="13.6">seguranças</w>
    <w id="13.7">"</w>
    <w id="13.8">...</w>
    <time id="T21E" value="00:01:22,647" />
    <time id="T22S" value="00:01:22,648" />
    <w id="13.9">tenham</w>
    <w id="13.10">de</w>
    <w id="13.11">esperar</w>
    <w id="13.12">aqui</w>
    <w id="13.13">fora</w>
    <w id="13.14">.</w>
    <time id="T22E" value="00:01:24,747" />
  </s>
  <s id="14">
    <time id="T23S" value="00:01:24,748" />
    <w id="14.1">É</w>
    <w id="14.2">claro</w>
    <w id="14.3">.</w>
    <time id="T23E" value="00:01:26,318" />
  </s>
  <s id="15">
    <time id="T24S" value="00:02:12,329" />
    <w id="15.1">Nós</w>
    <w id="15.2">,</w>
    <w id="15.3">do</w>
    <w id="15.4">Conselho</w>
    <w id="15.5">dos</w>
    <w id="15.6">Cinco</w>
    <w id="15.7">...</w>
    <time id="T24E" value="00:02:14,305" />
    <time id="T25S" value="00:02:14,506" />
    <w id="15.8">estamos</w>
    <w id="15.9">honrados</w>
    <w id="15.10">,</w>
    <w id="15.11">mas</w>
    <w id="15.12">surpreendidos</w>
    <w id="15.13">...</w>
    <time id="T25E" value="00:02:16,466" />
    <time id="T26S" value="00:02:16,467" />
    <w id="15.14">que</w>
    <w id="15.15">a</w>
    <w id="15.16">senhora</w>
    <w id="15.17">tenha</w>
    <w id="15.18">viajado</w>
    <w id="15.19">tanto</w>
    <w id="15.20">...</w>
    <time id="T26E" value="00:02:18,450" />
    <time id="T27S" value="00:02:18,451" />
    <w id="15.21">por</w>
    <w id="15.22">uma</w>
    <w id="15.23">mera</w>
    <w id="15.24">transferência</w>
    <w id="15.25">bancária</w>
    <w id="15.26">.</w>
    <time id="T27E" value="00:02:20,611" />
  </s>
  <s id="16">
    <time id="T28S" value="00:02:20,612" />
    <w id="16.1">Uma</w>
    <w id="16.2">transferência</w>
    <w id="16.3">que</w>
    <w id="16.4">ainda</w>
    <w id="16.5">não</w>
    <w id="16.6">se</w>
    <w id="16.7">concretizou</w>
    <w id="16.8">.</w>
    <time id="T28E" value="00:02:23,155" />
  </s>
  <s id="17">
    <time id="T29S" value="00:02:23,156" />
    <w id="17.1">Por</w>
    <w id="17.2">solicitação</w>
    <w id="17.3">do</w>
    <w id="17.4">Chanceler</w>
    <w id="17.5">Supremo</w>
    <w id="17.6">...</w>
    <time id="T29E" value="00:02:25,591" />
    <time id="T30S" value="00:02:25,592" />
    <w id="17.7">estou</w>
    <w id="17.8">aqui</w>
    <w id="17.9">para</w>
    <w id="17.10">acelerar</w>
    <w id="17.11">o</w>
    <w id="17.12">assunto</w>
    <w id="17.13">.</w>
    <time id="T30E" value="00:02:27,543" />
  </s>
  <s id="18">
    <time id="T31S" value="00:02:27,544" />
    <w id="18.1">Claro</w>
    <w id="18.2">.</w>
    <time id="T31E" value="00:02:28,886" />
  </s>
  <s id="19">
    <time id="T32S" value="00:02:28,887" />
    <w id="19.1">Somente</w>
    <w id="19.2">pedimos</w>
    <w id="19.3">que</w>
    <w id="19.4">a</w>
    <w id="19.5">senhora</w>
    <w id="19.6">se</w>
    <w id="19.7">encontre</w>
    <w id="19.8">...</w>
    <time id="T32E" value="00:02:31,229" />
    <time id="T33S" value="00:02:31,230" />
    <w id="19.9">com</w>
    <w id="19.10">o</w>
    <w id="19.11">nosso</w>
    <w id="19.12">representante</w>
    <w id="19.13">especial</w>
    <w id="19.14">,</w>
    <time id="T33E" value="00:02:33,040" />
    <time id="T34S" value="00:02:33,041" />
    <w id="19.15">que</w>
    <w id="19.16">irá</w>
    <w id="19.17">rever</w>
    <w id="19.18">os</w>
    <w id="19.19">termos</w>
    <w id="19.20">...</w>
    <time id="T34E" value="00:02:34,712" />
    <time id="T35S" value="00:02:34,713" />
    <w id="19.21">e</w>
    <w id="19.22">condições</w>
    <w id="19.23">do</w>
    <w id="19.24">seu</w>
    <w id="19.25">empréstimo</w>
    <w id="19.26">.</w>
    <time id="T35E" value="00:02:36,713" />
  </s>
  <s id="20">
    <time id="T36S" value="00:02:45,278" />
    <w id="20.1">Senadora</w>
    <w id="20.2">Amidala</w>
    <w id="20.3">.</w>
    <time id="T36E" value="00:02:46,980" />
  </s>
  <s id="21">
    <time id="T37S" value="00:02:47,781" />
    <w id="21.1">Clovis</w>
    <w id="21.2">!</w>
    <time id="T37E" value="00:02:49,090" />
  </s>
  <s id="22">
    <time id="T38S" value="00:02:49,091" />
    <w id="22.1">Os</w>
    <w id="22.2">dois</w>
    <w id="22.3">já</w>
    <w id="22.4">se</w>
    <w id="22.5">conhecem</w>
    <w id="22.6">?</w>
    <time id="T38E" value="00:02:51,367" />
  </s>
  <s id="23">
    <time id="T39S" value="00:02:51,968" />
    <w id="23.1">Senhor</w>
    <w id="23.2">,</w>
    <w id="23.3">gostava</w>
    <w id="23.4">muito</w>
    <w id="23.5">que</w>
    <w id="23.6">esta</w>
    <w id="23.7">transacção</w>
    <w id="23.8">...</w>
    <time id="T39E" value="00:02:54,286" />
    <time id="T40S" value="00:02:54,287" />
    <w id="23.9">fosse</w>
    <w id="23.10">livre</w>
    <w id="23.11">de</w>
    <w id="23.12">preconceitos</w>
    <w id="23.13">e</w>
    <w id="23.14">fidelidades</w>
    <w id="23.15">partidárias</w>
    <w id="23.16">.</w>
    <time id="T40E" value="00:02:56,873" />
  </s>
  <s id="24">
    <time id="T41S" value="00:02:56,874" />
    <w id="24.1">Este</w>
    <w id="24.2">homem</w>
    <w id="24.3">é</w>
    <w id="24.4">um</w>
    <w id="24.5">Separatista</w>
    <w id="24.6">conhecido</w>
    <w id="24.7">...</w>
    <time id="T41E" value="00:02:58,819" />
    <time id="T42S" value="00:02:59,220" />
    <w id="24.8">e</w>
    <w id="24.9">um</w>
    <w id="24.10">traidor</w>
    <w id="24.11">da</w>
    <w id="24.12">República</w>
    <w id="24.13">.</w>
    <time id="T42E" value="00:03:00,919" />
  </s>
  <s id="25">
    <time id="T43S" value="00:03:00,920" />
    <w id="25.1">Padmé</w>
    <w id="25.2">.</w>
    <time id="T43E" value="00:03:02,312" />
  </s>
  <s id="26">
    <time id="T44S" value="00:03:02,313" />
    <w id="26.1">Posso</w>
    <w id="26.2">assegurar-lhe</w>
    <w id="26.3">que</w>
    <w id="26.4">Rush</w>
    <w id="26.5">Clovis</w>
    <w id="26.6">...</w>
    <time id="T44E" value="00:03:04,796" />
    <time id="T45S" value="00:03:04,797" />
    <w id="26.7">é</w>
    <w id="26.8">o</w>
    <w id="26.9">nosso</w>
    <w id="26.10">melhor</w>
    <w id="26.11">negociador</w>
    <w id="26.12">e</w>
    <w id="26.13">de</w>
    <w id="26.14">maior</w>
    <w id="26.15">confiança</w>
    <w id="26.16">.</w>
    <time id="T45E" value="00:03:07,499" />
  </s>
  <s id="27">
    <time id="T46S" value="00:03:07,500" />
    <w id="27.1">Lamento</w>
    <w id="27.2">muito</w>
    <w id="27.3">,</w>
    <w id="27.4">cavalheiros</w>
    <w id="27.5">...</w>
    <time id="T46E" value="00:03:09,235" />
    <time id="T47S" value="00:03:09,636" />
    <w id="27.6">mas</w>
    <w id="27.7">insisto</w>
    <w id="27.8">que</w>
    <w id="27.9">este</w>
    <w id="27.10">homem</w>
    <w id="27.11">seja</w>
    <w id="27.12">afastado</w>
    <w id="27.13">das</w>
    <w id="27.14">negociações</w>
    <w id="27.15">.</w>
    <time id="T47E" value="00:03:13,098" />
  </s>
  <s id="28">
    <time id="T48S" value="00:03:13,099" />
    <w id="28.1">Até</w>
    <w id="28.2">que</w>
    <w id="28.3">isso</w>
    <w id="28.4">seja</w>
    <w id="28.5">feito</w>
    <w id="28.6">,</w>
    <w id="28.7">não</w>
    <w id="28.8">temos</w>
    <w id="28.9">mais</w>
    <w id="28.10">nada</w>
    <w id="28.11">a</w>
    <w id="28.12">discutir</w>
    <w id="28.13">.</w>
    <time id="T48E" value="00:03:16,228" />
  </s>
  <s id="29">
    <time id="T49S" value="00:03:38,958" />
    <w id="29.1">A</w>
    <w id="29.2">Milady</w>
    <w id="29.3">já</w>
    <w id="29.4">não</w>
    <w id="29.5">precisa</w>
    <w id="29.6">mais</w>
    <w id="29.7">da</w>
    <w id="29.8">tua</w>
    <w id="29.9">ajuda</w>
    <w id="29.10">,</w>
    <w id="29.11">por</w>
    <w id="29.12">hoje</w>
    <w id="29.13">.</w>
    <time id="T49E" value="00:03:41,801" />
  </s>
  <s id="30">
    <time id="T50S" value="00:03:41,802" />
    <w id="30.1">Obrigada</w>
    <w id="30.2">.</w>
    <time id="T50E" value="00:03:43,263" />
  </s>
  <s id="31">
    <time id="T51S" value="00:03:48,968" />
    <w id="31.1">Milady</w>
    <w id="31.2">!</w>
  </s>
  <s id="32">
    <w id="32.1">Cuidado</w>
    <w id="32.2">!</w>
    <time id="T51E" value="00:03:50,676" />
  </s>
  <s id="33">
    <time id="T52S" value="00:03:50,677" />
    <w id="33.1">Parava</w>
    <w id="33.2">aí</w>
    <w id="33.3">mesmo</w>
    <w id="33.4">,</w>
    <w id="33.5">se</w>
    <w id="33.6">fosse</w>
    <w id="33.7">a</w>
    <w id="33.8">ti</w>
    <w id="33.9">.</w>
    <time id="T52E" value="00:03:53,379" />
  </s>
  <s id="34">
    <time id="T53S" value="00:03:54,080" />
    <w id="34.1">Como</w>
    <w id="34.2">é</w>
    <w id="34.3">que</w>
    <w id="34.4">entraste</w>
    <w id="34.5">com</w>
    <w id="34.6">um</w>
    <w id="34.7">blaster</w>
    <w id="34.8">na</w>
    <w id="34.9">Zona</w>
    <w id="34.10">Neutra</w>
    <w id="34.11">?</w>
    <time id="T53E" value="00:03:57,442" />
  </s>
  <s id="35">
    <time id="T54S" value="00:03:57,443" />
    <w id="35.1">Temos</w>
    <w id="35.2">os</w>
    <w id="35.3">nossos</w>
    <w id="35.4">meios</w>
    <w id="35.5">.</w>
    <time id="T54E" value="00:03:59,269" />
  </s>
  <s id="36">
    <time id="T55S" value="00:03:59,270" />
    <w id="36.1">Agora</w>
    <w id="36.2">,</w>
    <w id="36.3">porque</w>
    <w id="36.4">é</w>
    <w id="36.5">que</w>
    <w id="36.6">invadiu</w>
    <w id="36.7">os</w>
    <w id="36.8">meus</w>
    <w id="36.9">aposentos</w>
    <w id="36.10">?</w>
    <time id="T55E" value="00:04:02,438" />
  </s>
  <s id="37">
    <time id="T56S" value="00:04:02,439" />
    <w id="37.1">Padmé</w>
    <w id="37.2">,</w>
    <w id="37.3">não</w>
    <w id="37.4">entendes</w>
    <w id="37.5">o</w>
    <w id="37.6">que</w>
    <w id="37.7">está</w>
    <w id="37.8">a</w>
    <w id="37.9">acontecer</w>
    <w id="37.10">aqui</w>
    <w id="37.11">.</w>
    <time id="T56E" value="00:04:05,233" />
  </s>
  <s id="38">
    <time id="T57S" value="00:04:05,234" />
    <w id="38.1">Preciso</w>
    <w id="38.2">da</w>
    <w id="38.3">tua</w>
    <w id="38.4">ajuda</w>
    <w id="38.5">.</w>
    <time id="T57E" value="00:04:06,776" />
  </s>
  <s id="39">
    <time id="T58S" value="00:04:06,777" />
    <w id="39.1">Da</w>
    <w id="39.2">última</w>
    <w id="39.3">vez</w>
    <w id="39.4">que</w>
    <w id="39.5">precisaste</w>
    <w id="39.6">,</w>
    <w id="39.7">acabei</w>
    <w id="39.8">envenenada</w>
    <w id="39.9">...</w>
    <time id="T58E" value="00:04:09,621" />
    <time id="T59S" value="00:04:09,622" />
    <w id="39.10">e</w>
    <w id="39.11">não</w>
    <w id="39.12">fizeste</w>
    <w id="39.13">nada</w>
    <w id="39.14">!</w>
    <time id="T59E" value="00:04:10,947" />
  </s>
  <s id="40">
    <time id="T60S" value="00:04:11,248" />
    <w id="40.1">Isso</w>
    <w id="40.2">não</w>
    <w id="40.3">é</w>
    <w id="40.4">verdade</w>
    <w id="40.5">.</w>
  </s>
  <s id="41">
    <w id="41.1">Tu</w>
    <w id="41.2">roubaste-me</w>
    <w id="41.3">informações</w>
    <w id="41.4">.</w>
    <time id="T60E" value="00:04:14,208" />
  </s>
  <s id="42">
    <time id="T61S" value="00:04:14,609" />
    <w id="42.1">Que</w>
    <w id="42.2">revelaram</w>
    <w id="42.3">uma</w>
    <w id="42.4">fábrica</w>
    <w id="42.5">separatista</w>
    <w id="42.6">de</w>
    <w id="42.7">dróides</w>
    <w id="42.8">...</w>
    <time id="T61E" value="00:04:17,120" />
    <time id="T62S" value="00:04:17,121" />
    <w id="42.9">patrocinada</w>
    <w id="42.10">por</w>
    <w id="42.11">ti</w>
    <w id="42.12">!</w>
    <time id="T62E" value="00:04:18,913" />
  </s>
  <s id="43">
    <time id="T63S" value="00:04:19,714" />
    <w id="43.1">Olha</w>
    <w id="43.2">,</w>
    <w id="43.3">não</w>
    <w id="43.4">é</w>
    <w id="43.5">seguro</w>
    <w id="43.6">.</w>
    <time id="T63E" value="00:04:21,457" />
  </s>
  <s id="44">
    <time id="T64S" value="00:04:21,458" />
    <w id="44.1">Não</w>
    <w id="44.2">podemos</w>
    <w id="44.3">falar</w>
    <w id="44.4">aqui</w>
    <w id="44.5">.</w>
    <time id="T64E" value="00:04:23,002" />
  </s>
  <s id="45">
    <time id="T65S" value="00:04:26,880" />
    <w id="45.1">-</w>
    <w id="45.2">Senadora</w>
    <w id="45.3">,</w>
    <w id="45.4">não</w>
    <w id="45.5">acho</w>
    <w id="45.6">que</w>
    <w id="45.7">...</w>
  </s>
  <s id="46">
    <w id="46.1">-</w>
    <w id="46.2">Está</w>
    <w id="46.3">tudo</w>
    <w id="46.4">bem</w>
    <w id="46.5">...</w>
    <time id="T65E" value="00:04:29,799" />
  </s>
  <s id="47">
    <time id="T66S" value="00:04:29,800" />
    <w id="47.1">Quero</w>
    <w id="47.2">ouvir</w>
    <w id="47.3">o</w>
    <w id="47.4">que</w>
    <w id="47.5">é</w>
    <w id="47.6">que</w>
    <w id="47.7">ele</w>
    <w id="47.8">tem</w>
    <w id="47.9">a</w>
    <w id="47.10">dizer</w>
    <w id="47.11">.</w>
    <time id="T66E" value="00:04:32,220" />
  </s>
  <s id="48">
    <time id="T67S" value="00:04:47,384" />
    <w id="48.1">A</w>
    <w id="48.2">verdade</w>
    <w id="48.3">é</w>
    <w id="48.4">que</w>
    <w id="48.5">a</w>
    <w id="48.6">economia</w>
    <w id="48.7">da</w>
    <w id="48.8">guerra</w>
    <w id="48.9">está</w>
    <w id="48.10">falida</w>
    <w id="48.11">.</w>
    <time id="T67E" value="00:04:51,354" />
  </s>
  <s id="49">
    <time id="T68S" value="00:04:51,355" />
    <w id="49.1">Vieste</w>
    <w id="49.2">fazer</w>
    <w id="49.3">o</w>
    <w id="49.4">empréstimo</w>
    <w id="49.5">...</w>
    <time id="T68E" value="00:04:53,080" />
    <time id="T69S" value="00:04:53,081" />
    <w id="49.6">mas</w>
    <w id="49.7">posso</w>
    <w id="49.8">assegurar-te</w>
    <w id="49.9">,</w>
    <w id="49.10">não</w>
    <w id="49.11">há</w>
    <w id="49.12">dinheiro</w>
    <w id="49.13">no</w>
    <w id="49.14">banco</w>
    <w id="49.15">.</w>
    <time id="T69E" value="00:04:55,992" />
  </s>
  <s id="50">
    <time id="T70S" value="00:04:55,993" />
    <w id="50.1">Isso</w>
    <w id="50.2">é</w>
    <w id="50.3">um</w>
    <w id="50.4">absurdo</w>
    <w id="50.5">!</w>
    <time id="T70E" value="00:04:57,576" />
  </s>
  <s id="51">
    <time id="T71S" value="00:04:57,577" />
    <w id="51.1">Eles</w>
    <w id="51.2">queriam</w>
    <w id="51.3">fazer</w>
    <w id="51.4">o</w>
    <w id="51.5">depósito</w>
    <w id="51.6">hoje</w>
    <w id="51.7">.</w>
    <time id="T71E" value="00:04:59,704" />
  </s>
  <s id="52">
    <time id="T72S" value="00:05:00,105" />
    <w id="52.1">Eles</w>
    <w id="52.2">vão</w>
    <w id="52.3">dar-te</w>
    <w id="52.4">uma</w>
    <w id="52.5">primeira</w>
    <w id="52.6">parcela</w>
    <w id="52.7">,</w>
    <w id="52.8">sim</w>
    <w id="52.9">...</w>
    <time id="T72E" value="00:05:03,291" />
    <time id="T73S" value="00:05:03,292" />
    <w id="52.10">mas</w>
    <w id="52.11">estão</w>
    <w id="52.12">a</w>
    <w id="52.13">roubar</w>
    <w id="52.14">de</w>
    <w id="52.15">um</w>
    <w id="52.16">lado</w>
    <w id="52.17">para</w>
    <w id="52.18">salvar</w>
    <w id="52.19">o</w>
    <w id="52.20">outro</w>
    <w id="52.21">.</w>
    <time id="T73E" value="00:05:06,002" />
  </s>
  <s id="53">
    <time id="T74S" value="00:05:06,003" />
    <w id="53.1">Todo</w>
    <w id="53.2">o</w>
    <w id="53.3">Clã</w>
    <w id="53.4">Bancário</w>
    <w id="53.5">está</w>
    <w id="53.6">à</w>
    <w id="53.7">beira</w>
    <w id="53.8">do</w>
    <w id="53.9">colapso</w>
    <w id="53.10">.</w>
    <time id="T74E" value="00:05:08,880" />
  </s>
  <s id="54">
    <time id="T75S" value="00:05:08,881" />
    <w id="54.1">Colapso</w>
    <w id="54.2">?</w>
  </s>
  <s id="55">
    <w id="55.1">Onde</w>
    <w id="55.2">é</w>
    <w id="55.3">que</w>
    <w id="55.4">estão</w>
    <w id="55.5">as</w>
    <w id="55.6">prova</w>
    <w id="55.7">disso</w>
    <w id="55.8">?</w>
    <time id="T75E" value="00:05:11,341" />
  </s>
  <s id="56">
    <time id="T76S" value="00:05:11,342" />
    <w id="56.1">No</w>
    <w id="56.2">cofre</w>
    <w id="56.3">.</w>
  </s>
  <s id="57">
    <w id="57.1">As</w>
    <w id="57.2">contas</w>
    <w id="57.3">estão</w>
    <w id="57.4">seladas</w>
    <w id="57.5">lá</w>
    <w id="57.6">.</w>
    <time id="T76E" value="00:05:13,885" />
  </s>
  <s id="58">
    <time id="T77S" value="00:05:13,886" />
    <w id="58.1">Ninguém</w>
    <w id="58.2">pode</w>
    <w id="58.3">vê-las</w>
    <w id="58.4">,</w>
    <w id="58.5">a</w>
    <w id="58.6">não</w>
    <w id="58.7">ser</w>
    <w id="58.8">o</w>
    <w id="58.9">Conselho</w>
    <w id="58.10">do</w>
    <w id="58.11">Cinco</w>
    <w id="58.12">.</w>
    <time id="T77E" value="00:05:16,478" />
  </s>
  <s id="59">
    <time id="T78S" value="00:05:17,347" />
    <w id="59.1">Que</w>
    <w id="59.2">conveniente</w>
    <w id="59.3">.</w>
    <time id="T78E" value="00:05:18,849" />
  </s>
  <s id="60">
    <time id="T79S" value="00:05:26,181" />
    <w id="60.1">Agora</w>
    <w id="60.2">que</w>
    <w id="60.3">estás</w>
    <w id="60.4">aqui</w>
    <w id="60.5">...</w>
    <time id="T79E" value="00:05:27,583" />
    <time id="T80S" value="00:05:27,584" />
    <w id="60.6">deves</w>
    <w id="60.7">aumentar</w>
    <w id="60.8">a</w>
    <w id="60.9">pressão</w>
    <w id="60.10">sobre</w>
    <w id="60.11">eles</w>
    <w id="60.12">.</w>
    <time id="T80E" value="00:05:29,583" />
  </s>
  <s id="61">
    <time id="T81S" value="00:05:29,584" />
    <w id="61.1">E</w>
    <w id="61.2">fazer</w>
    <w id="61.3">o</w>
    <w id="61.4">quê</w>
    <w id="61.5">,</w>
    <w id="61.6">exactamente</w>
    <w id="61.7">?</w>
    <time id="T81E" value="00:05:31,228" />
  </s>
  <s id="62">
    <time id="T82S" value="00:05:32,029" />
    <w id="62.1">Ajuda-me</w>
    <w id="62.2">a</w>
    <w id="62.3">ter</w>
    <w id="62.4">acesso</w>
    <w id="62.5">ao</w>
    <w id="62.6">cofre</w>
    <w id="62.7">.</w>
    <time id="T82E" value="00:05:34,488" />
  </s>
  <s id="63">
    <time id="T83S" value="00:05:34,489" />
    <w id="63.1">Estás</w>
    <w id="63.2">louco</w>
    <w id="63.3">em</w>
    <w id="63.4">pensar</w>
    <w id="63.5">que</w>
    <w id="63.6">iria</w>
    <w id="63.7">confiar</w>
    <w id="63.8">em</w>
    <w id="63.9">ti</w>
    <w id="63.10">.</w>
    <time id="T83E" value="00:05:37,450" />
  </s>
  <s id="64">
    <time id="T84S" value="00:05:38,451" />
    <w id="64.1">Lamento</w>
    <w id="64.2">muito</w>
    <w id="64.3">,</w>
    <w id="64.4">mas</w>
    <w id="64.5">não</w>
    <w id="64.6">posso</w>
    <w id="64.7">ajudar-te</w>
    <w id="64.8">.</w>
    <time id="T84E" value="00:05:40,787" />
  </s>
  <s id="65">
    <time id="T85S" value="00:05:45,084" />
    <w id="65.1">Tira</w>
    <w id="65.2">as</w>
    <w id="65.3">mãos</w>
    <w id="65.4">de</w>
    <w id="65.5">cima</w>
    <w id="65.6">de</w>
    <w id="65.7">mim</w>
    <w id="65.8">!</w>
    <time id="T85E" value="00:05:46,919" />
  </s>
  <s id="66">
    <time id="T86S" value="00:05:49,304" />
    <w id="66.1">Arrisquei</w>
    <w id="66.2">tudo</w>
    <w id="66.3">para</w>
    <w id="66.4">dizer-te</w>
    <w id="66.5">isto</w>
    <w id="66.6">!</w>
    <time id="T86E" value="00:05:51,639" />
  </s>
  <s id="67">
    <time id="T87S" value="00:05:51,640" />
    <w id="67.1">Não</w>
    <w id="67.2">vês</w>
    <w id="67.3">que</w>
    <w id="67.4">estão</w>
    <w id="67.5">a</w>
    <w id="67.6">tentar</w>
    <w id="67.7">matar-me</w>
    <w id="67.8">,</w>
    <w id="67.9">por</w>
    <w id="67.10">causa</w>
    <w id="67.11">do</w>
    <w id="67.12">que</w>
    <w id="67.13">sei</w>
    <w id="67.14">?</w>
    <time id="T87E" value="00:05:54,423" />
  </s>
  <s id="68">
    <time id="T88S" value="00:06:01,427" />
    <w id="68.1">Por</w>
    <w id="68.2">favor</w>
    <w id="68.3">,</w>
    <w id="68.4">acredita</w>
    <w id="68.5">em</w>
    <w id="68.6">mim</w>
    <w id="68.7">.</w>
    <time id="T88E" value="00:06:03,096" />
  </s>
  <s id="69">
    <time id="T89S" value="00:06:03,097" />
    <w id="69.1">O</w>
    <w id="69.2">nosso</w>
    <w id="69.3">passado</w>
    <w id="69.4">deve</w>
    <w id="69.5">servir</w>
    <w id="69.6">de</w>
    <w id="69.7">alguma</w>
    <w id="69.8">coisa</w>
    <w id="69.9">.</w>
    <time id="T89E" value="00:06:05,351" />
  </s>
  <s id="70">
    <time id="T90S" value="00:06:05,352" />
    <w id="70.1">Não</w>
    <w id="70.2">posso</w>
    <w id="70.3">ficar</w>
    <w id="70.4">aqui</w>
    <w id="70.5">.</w>
  </s>
  <s id="71">
    <w id="71.1">Pensa</w>
    <w id="71.2">no</w>
    <w id="71.3">que</w>
    <w id="71.4">te</w>
    <w id="71.5">pedi</w>
    <w id="71.6">.</w>
    <time id="T90E" value="00:06:08,346" />
  </s>
  <s id="72">
    <time id="T91S" value="00:06:34,215" />
    <w id="72.1">Se</w>
    <w id="72.2">o</w>
    <w id="72.3">que</w>
    <w id="72.4">está</w>
    <w id="72.5">a</w>
    <w id="72.6">dizer</w>
    <w id="72.7">é</w>
    <w id="72.8">verdade</w>
    <w id="72.9">...</w>
    <time id="T91E" value="00:06:36,363" />
    <time id="T92S" value="00:06:36,464" />
    <w id="72.10">então</w>
    <w id="72.11">essa</w>
    <w id="72.12">informação</w>
    <w id="72.13">que</w>
    <w id="72.14">o</w>
    <w id="72.15">Clovis</w>
    <w id="72.16">está</w>
    <w id="72.17">a</w>
    <w id="72.18">oferecer</w>
    <w id="72.19">...</w>
    <time id="T92E" value="00:06:39,162" />
    <time id="T93S" value="00:06:39,263" />
    <w id="72.20">é</w>
    <w id="72.21">vital</w>
    <w id="72.22">para</w>
    <w id="72.23">a</w>
    <w id="72.24">nossa</w>
    <w id="72.25">segurança</w>
    <w id="72.26">.</w>
    <time id="T93E" value="00:06:42,016" />
  </s>
  <s id="73">
    <time id="T94S" value="00:06:42,317" />
    <w id="73.1">Preciso</w>
    <w id="73.2">que</w>
    <w id="73.3">seja</w>
    <w id="73.4">muito</w>
    <w id="73.5">objectiva</w>
    <w id="73.6">sobre</w>
    <w id="73.7">este</w>
    <w id="73.8">assunto</w>
    <w id="73.9">.</w>
    <time id="T94E" value="00:06:45,366" />
  </s>
  <s id="74">
    <time id="T95S" value="00:06:45,567" />
    <w id="74.1">Para</w>
    <w id="74.2">a</w>
    <w id="74.3">República</w>
    <w id="74.4">...</w>
    <time id="T95E" value="00:06:47,505" />
  </s>
  <s id="75">
    <time id="T96S" value="00:06:47,906" />
    <w id="75.1">Será</w>
    <w id="75.2">que</w>
    <w id="75.3">ele</w>
    <w id="75.4">está</w>
    <w id="75.5">a</w>
    <w id="75.6">dizer</w>
    <w id="75.7">a</w>
    <w id="75.8">verdade</w>
    <w id="75.9">?</w>
    <time id="T96E" value="00:06:49,909" />
  </s>
  <s id="76">
    <time id="T97S" value="00:06:49,910" />
    <w id="76.1">Sim</w>
    <w id="76.2">,</w>
    <w id="76.3">tenho</w>
    <w id="76.4">a</w>
    <w id="76.5">certeza</w>
    <w id="76.6">.</w>
    <time id="T97E" value="00:06:52,624" />
  </s>
  <s id="77">
    <time id="T98S" value="00:06:52,625" />
    <w id="77.1">Talvez</w>
    <w id="77.2">,</w>
    <w id="77.3">então</w>
    <w id="77.4">,</w>
    <w id="77.5">nesse</w>
    <w id="77.6">cenário</w>
    <w id="77.7">,</w>
    <time id="T98E" value="00:06:55,044" />
    <time id="T99S" value="00:06:55,045" />
    <w id="77.8">fosse</w>
    <w id="77.9">melhor</w>
    <w id="77.10">que</w>
    <w id="77.11">confiasse</w>
    <w id="77.12">num</w>
    <w id="77.13">velho</w>
    <w id="77.14">amigo</w>
    <w id="77.15">...</w>
    <time id="T99E" value="00:06:59,220" />
    <time id="T100S" value="00:06:59,221" />
    <w id="77.16">e</w>
    <w id="77.17">faça</w>
    <w id="77.18">o</w>
    <w id="77.19">que</w>
    <w id="77.20">ele</w>
    <w id="77.21">sugere</w>
    <w id="77.22">.</w>
    <time id="T100E" value="00:07:01,643" />
  </s>
  <s id="78">
    <time id="T101S" value="00:07:22,747" />
    <w id="78.1">Decidi</w>
    <w id="78.2">aceitar</w>
    <w id="78.3">Clovis</w>
    <w id="78.4">...</w>
    <time id="T101E" value="00:07:24,608" />
    <time id="T102S" value="00:07:24,609" />
    <w id="78.5">como</w>
    <w id="78.6">representante</w>
    <w id="78.7">desta</w>
    <w id="78.8">transacção</w>
    <w id="78.9">,</w>
    <time id="T102E" value="00:07:26,671" />
    <time id="T103S" value="00:07:26,672" />
    <w id="78.10">desde</w>
    <w id="78.11">que</w>
    <w id="78.12">possa</w>
    <w id="78.13">entrar</w>
    <w id="78.14">no</w>
    <w id="78.15">cofre</w>
    <w id="78.16">...</w>
    <time id="T103E" value="00:07:28,785" />
    <time id="T104S" value="00:07:28,786" />
    <w id="78.17">e</w>
    <w id="78.18">acompanhe</w>
    <w id="78.19">os</w>
    <w id="78.20">fundos</w>
    <w id="78.21">durante</w>
    <w id="78.22">todo</w>
    <w id="78.23">o</w>
    <w id="78.24">processo</w>
    <w id="78.25">.</w>
    <time id="T104E" value="00:07:31,748" />
  </s>
  <s id="79">
    <time id="T105S" value="00:07:31,749" />
    <w id="79.1">Nenhum</w>
    <w id="79.2">forasteiro</w>
    <w id="79.3">alguma</w>
    <w id="79.4">vez</w>
    <w id="79.5">,</w>
    <w id="79.6">entrou</w>
    <w id="79.7">nos</w>
    <w id="79.8">nossos</w>
    <w id="79.9">cofres</w>
    <w id="79.10">.</w>
    <time id="T105E" value="00:07:35,883" />
  </s>
  <s id="80">
    <time id="T106S" value="00:07:35,884" />
    <w id="80.1">Venho</w>
    <w id="80.2">com</w>
    <w id="80.3">a</w>
    <w id="80.4">autoridade</w>
    <w id="80.5">do</w>
    <w id="80.6">Chanceler</w>
    <w id="80.7">Supremo</w>
    <w id="80.8">.</w>
    <time id="T106E" value="00:07:38,806" />
  </s>
  <s id="81">
    <time id="T107S" value="00:07:38,807" />
    <w id="81.1">Se</w>
    <w id="81.2">têm</w>
    <w id="81.3">alguma</w>
    <w id="81.4">coisa</w>
    <w id="81.5">a</w>
    <w id="81.6">esconder</w>
    <w id="81.7">...</w>
    <time id="T107E" value="00:07:40,476" />
    <time id="T108S" value="00:07:40,477" />
    <w id="81.8">então</w>
    <w id="81.9">isso</w>
    <w id="81.10">é</w>
    <w id="81.11">uma</w>
    <w id="81.12">coisa</w>
    <w id="81.13">que</w>
    <w id="81.14">devemos</w>
    <w id="81.15">discutir</w>
    <w id="81.16">.</w>
    <time id="T108E" value="00:07:42,647" />
  </s>
  <s id="82">
    <time id="T109S" value="00:07:42,648" />
    <w id="82.1">Esconder</w>
    <w id="82.2">?</w>
    <time id="T109E" value="00:07:43,959" />
  </s>
  <s id="83">
    <time id="T110S" value="00:07:43,960" />
    <w id="83.1">Considerando</w>
    <w id="83.2">o</w>
    <w id="83.3">ataque</w>
    <w id="83.4">de</w>
    <w id="83.5">ontem</w>
    <w id="83.6">à</w>
    <w id="83.7">Senadora</w>
    <w id="83.8">...</w>
    <time id="T110E" value="00:07:46,673" />
    <time id="T111S" value="00:07:46,674" />
    <w id="83.9">é</w>
    <w id="83.10">justo</w>
    <w id="83.11">que</w>
    <w id="83.12">sejamos</w>
    <w id="83.13">transparentes</w>
    <w id="83.14">...</w>
    <time id="T111E" value="00:07:48,911" />
    <time id="T112S" value="00:07:48,912" />
    <w id="83.15">e</w>
    <w id="83.16">concordemos</w>
    <w id="83.17">com</w>
    <w id="83.18">estes</w>
    <w id="83.19">termos</w>
    <w id="83.20">.</w>
    <time id="T112E" value="00:07:50,831" />
  </s>
  <s id="84">
    <time id="T113S" value="00:07:50,832" />
    <w id="84.1">Que</w>
    <w id="84.2">mal</w>
    <w id="84.3">é</w>
    <w id="84.4">que</w>
    <w id="84.5">isso</w>
    <w id="84.6">nos</w>
    <w id="84.7">fará</w>
    <w id="84.8">?</w>
    <time id="T113E" value="00:07:52,377" />
  </s>
  <s id="85">
    <time id="T114S" value="00:07:57,137" />
    <w id="85.1">O</w>
    <w id="85.2">cofre</w>
    <w id="85.3">será</w>
    <w id="85.4">aberto</w>
    <w id="85.5">de</w>
    <w id="85.6">manhã</w>
    <w id="85.7">cedo</w>
    <w id="85.8">.</w>
    <time id="T114E" value="00:07:59,976" />
  </s>
  <s id="86">
    <time id="T115S" value="00:07:59,977" />
    <w id="86.1">Garanta</w>
    <w id="86.2">a</w>
    <w id="86.3">sua</w>
    <w id="86.4">presença</w>
    <w id="86.5">,</w>
    <w id="86.6">Senadora</w>
    <w id="86.7">.</w>
    <time id="T115E" value="00:08:02,857" />
  </s>
  <s id="87">
    <time id="T116S" value="00:08:20,520" />
    <w id="87.1">Onde</w>
    <w id="87.2">é</w>
    <w id="87.3">que</w>
    <w id="87.4">estamos</w>
    <w id="87.5">,</w>
    <w id="87.6">Clovis</w>
    <w id="87.7">?</w>
    <time id="T116E" value="00:08:23,151" />
  </s>
  <s id="88">
    <time id="T117S" value="00:08:23,152" />
    <w id="88.1">Esta</w>
    <w id="88.2">é</w>
    <w id="88.3">a</w>
    <w id="88.4">minha</w>
    <w id="88.5">residência</w>
    <w id="88.6">pessoal</w>
    <w id="88.7">.</w>
    <time id="T117E" value="00:08:25,697" />
  </s>
  <s id="89">
    <time id="T118S" value="00:08:25,698" />
    <w id="89.1">Um</w>
    <w id="89.2">bocado</w>
    <w id="89.3">remota</w>
    <w id="89.4">,</w>
    <w id="89.5">mas</w>
    <w id="89.6">teremos</w>
    <w id="89.7">mais</w>
    <w id="89.8">privacidade</w>
    <w id="89.9">aqui</w>
    <w id="89.10">.</w>
    <time id="T118E" value="00:08:29,289" />
  </s>
  <s id="90">
    <time id="T119S" value="00:08:38,678" />
    <w id="90.1">Assim</w>
    <w id="90.2">que</w>
    <w id="90.3">detone</w>
    <w id="90.4">a</w>
    <w id="90.5">carga</w>
    <w id="90.6">na</w>
    <w id="90.7">fonte</w>
    <w id="90.8">de</w>
    <w id="90.9">energia</w>
    <w id="90.10">principal</w>
    <w id="90.11">,</w>
    <time id="T119E" value="00:08:42,274" />
    <time id="T120S" value="00:08:42,275" />
    <w id="90.12">o</w>
    <w id="90.13">cofre</w>
    <w id="90.14">entrará</w>
    <w id="90.15">em</w>
    <w id="90.16">imediato</w>
    <w id="90.17">fecho</w>
    <w id="90.18">.</w>
    <time id="T120E" value="00:08:45,407" />
  </s>
  <s id="91">
    <time id="T121S" value="00:08:49,525" />
    <w id="91.1">Ninguém</w>
    <w id="91.2">entrará</w>
    <w id="91.3">ou</w>
    <w id="91.4">sairá</w>
    <w id="91.5">.</w>
    <time id="T121E" value="00:08:51,412" />
  </s>
  <s id="92">
    <time id="T122S" value="00:08:51,413" />
    <w id="92.1">Isso</w>
    <w id="92.2">vai</w>
    <w id="92.3">dar-lhe</w>
    <w id="92.4">muito</w>
    <w id="92.5">pouco</w>
    <w id="92.6">tempo</w>
    <w id="92.7">...</w>
    <time id="T122E" value="00:08:53,123" />
    <time id="T123S" value="00:08:53,124" />
    <w id="92.8">antes</w>
    <w id="92.9">do</w>
    <w id="92.10">gerador</w>
    <w id="92.11">de</w>
    <w id="92.12">emergência</w>
    <w id="92.13">se</w>
    <w id="92.14">ligar</w>
    <w id="92.15">e</w>
    <w id="92.16">assumir</w>
    <w id="92.17">.</w>
    <time id="T123E" value="00:08:56,566" />
  </s>
  <s id="93">
    <time id="T124S" value="00:08:57,467" />
    <w id="93.1">Então</w>
    <w id="93.2">usará</w>
    <w id="93.3">isto</w>
    <w id="93.4">para</w>
    <w id="93.5">localizar</w>
    <w id="93.6">...</w>
    <time id="T124E" value="00:08:59,338" />
    <time id="T125S" value="00:08:59,339" />
    <w id="93.7">os</w>
    <w id="93.8">arquivos</w>
    <w id="93.9">exactos</w>
    <w id="93.10">e</w>
    <w id="93.11">baixá-los</w>
    <w id="93.12">para</w>
    <w id="93.13">o</w>
    <w id="93.14">computador</w>
    <w id="93.15">principal</w>
    <w id="93.16">.</w>
    <time id="T125E" value="00:09:02,339" />
  </s>
  <s id="94">
    <time id="T126S" value="00:09:04,173" />
    <w id="94.1">O</w>
    <w id="94.2">cofre</w>
    <w id="94.3">é</w>
    <w id="94.4">um</w>
    <w id="94.5">dos</w>
    <w id="94.6">mais</w>
    <w id="94.7">seguros</w>
    <w id="94.8">da</w>
    <w id="94.9">Galáxia</w>
    <w id="94.10">,</w>
    <time id="T126E" value="00:09:06,345" />
    <time id="T127S" value="00:09:06,346" />
    <w id="94.11">mas</w>
    <w id="94.12">foi</w>
    <w id="94.13">feito</w>
    <w id="94.14">para</w>
    <w id="94.15">manter</w>
    <w id="94.16">as</w>
    <w id="94.17">pessoas</w>
    <w id="94.18">fora</w>
    <w id="94.19">.</w>
    <time id="T127E" value="00:09:08,749" />
  </s>
  <s id="95">
    <time id="T128S" value="00:09:10,328" />
    <w id="95.1">Assim</w>
    <w id="95.2">que</w>
    <w id="95.3">estiver</w>
    <w id="95.4">dentro</w>
    <w id="95.5">e</w>
    <w id="95.6">a</w>
    <w id="95.7">energia</w>
    <w id="95.8">cair</w>
    <w id="95.9">...</w>
    <time id="T128E" value="00:09:13,034" />
    <time id="T129S" value="00:09:13,235" />
    <w id="95.10">há</w>
    <w id="95.11">pouco</w>
    <w id="95.12">que</w>
    <w id="95.13">possam</w>
    <w id="95.14">fazer</w>
    <w id="95.15">.</w>
    <time id="T129E" value="00:09:15,088" />
  </s>
  <s id="96">
    <time id="T130S" value="00:09:21,394" />
    <w id="96.1">Faz</w>
    <w id="96.2">isso</w>
    <w id="96.3">parecer</w>
    <w id="96.4">fácil</w>
    <w id="96.5">.</w>
    <time id="T130E" value="00:09:23,222" />
  </s>
  <s id="97">
    <time id="T131S" value="00:09:23,223" />
    <w id="97.1">Se</w>
    <w id="97.2">não</w>
    <w id="97.3">se</w>
    <w id="97.4">importa</w>
    <w id="97.5">,</w>
    <w id="97.6">Senadora</w>
    <w id="97.7">,</w>
    <w id="97.8">vou</w>
    <w id="97.9">retirar-me</w>
    <w id="97.10">.</w>
    <time id="T131E" value="00:09:26,897" />
  </s>
  <s id="98">
    <time id="T132S" value="00:09:26,898" />
    <w id="98.1">Claro</w>
    <w id="98.2">,</w>
    <w id="98.3">Teckla</w>
    <w id="98.4">.</w>
    <time id="T132E" value="00:09:29,033" />
  </s>
  <s id="99">
    <time id="T133S" value="00:09:29,034" />
    <w id="99.1">A</w>
    <w id="99.2">informação</w>
    <w id="99.3">que</w>
    <w id="99.4">apanharmos</w>
    <w id="99.5">amanhã</w>
    <w id="99.6">...</w>
    <time id="T133E" value="00:09:31,164" />
    <time id="T134S" value="00:09:31,165" />
    <w id="99.7">pode</w>
    <w id="99.8">expor</w>
    <w id="99.9">os</w>
    <w id="99.10">reais</w>
    <w id="99.11">criminosos</w>
    <w id="99.12">por</w>
    <w id="99.13">trás</w>
    <w id="99.14">desta</w>
    <w id="99.15">guerra</w>
    <w id="99.16">.</w>
    <time id="T134E" value="00:09:34,554" />
  </s>
  <s id="100">
    <time id="T135S" value="00:09:34,655" />
    <w id="100.1">Esses</w>
    <w id="100.2">são</w>
    <w id="100.3">os</w>
    <w id="100.4">capitalistas</w>
    <w id="100.5">da</w>
    <w id="100.6">guerra</w>
    <w id="100.7">.</w>
    <time id="T135E" value="00:09:36,444" />
  </s>
  <s id="101">
    <time id="T136S" value="00:09:36,545" />
    <w id="101.1">Já</w>
    <w id="101.2">os</w>
    <w id="101.3">expus</w>
    <w id="101.4">antes</w>
    <w id="101.5">.</w>
  </s>
  <s id="102">
    <w id="102.1">Ninguém</w>
    <w id="102.2">se</w>
    <w id="102.3">importa</w>
    <w id="102.4">.</w>
    <time id="T136E" value="00:09:39,884" />
  </s>
  <s id="103">
    <time id="T137S" value="00:09:39,885" />
    <w id="103.1">A</w>
    <w id="103.2">verdade</w>
    <w id="103.3">não</w>
    <w id="103.4">está</w>
    <w id="103.5">no</w>
    <w id="103.6">campo</w>
    <w id="103.7">de</w>
    <w id="103.8">batalha</w>
    <w id="103.9">.</w>
    <time id="T137E" value="00:09:43,951" />
  </s>
  <s id="104">
    <time id="T138S" value="00:09:46,071" />
    <w id="104.1">É</w>
    <w id="104.2">tarde</w>
    <w id="104.3">.</w>
    <time id="T138E" value="00:09:47,568" />
  </s>
  <s id="105">
    <time id="T139S" value="00:09:48,369" />
    <w id="105.1">Boa</w>
    <w id="105.2">noite</w>
    <w id="105.3">,</w>
    <w id="105.4">Clovis</w>
    <w id="105.5">.</w>
    <time id="T139E" value="00:09:50,748" />
  </s>
  <s id="106">
    <time id="T140S" value="00:11:07,455" />
    <w id="106.1">Clovis</w>
    <w id="106.2">,</w>
    <w id="106.3">aonde</w>
    <w id="106.4">vais</w>
    <w id="106.5">?</w>
    <time id="T140E" value="00:11:11,053" />
  </s>
  <s id="107">
    <time id="T141S" value="00:11:11,054" />
    <w id="107.1">Tenho</w>
    <w id="107.2">compromissos</w>
    <w id="107.3">a</w>
    <w id="107.4">cumprir</w>
    <w id="107.5">.</w>
    <time id="T141E" value="00:11:13,425" />
  </s>
  <s id="108">
    <time id="T142S" value="00:11:13,426" />
    <w id="108.1">Esta</w>
    <w id="108.2">ideia</w>
    <w id="108.3">foi</w>
    <w id="108.4">tua</w>
    <w id="108.5">.</w>
    <time id="T142E" value="00:11:15,890" />
  </s>
  <s id="109">
    <time id="T143S" value="00:11:15,891" />
    <w id="109.1">Gostaria</w>
    <w id="109.2">que</w>
    <w id="109.3">esperasses</w>
    <w id="109.4">o</w>
    <w id="109.5">retorno</w>
    <w id="109.6">da</w>
    <w id="109.7">Senadora</w>
    <w id="109.8">.</w>
    <time id="T143E" value="00:11:19,615" />
  </s>
  <s id="110">
    <time id="T144S" value="00:11:32,927" />
    <w id="110.1">Se</w>
    <w id="110.2">não</w>
    <w id="110.3">se</w>
    <w id="110.4">importar</w>
    <w id="110.5">de</w>
    <w id="110.6">me</w>
    <w id="110.7">seguir</w>
    <w id="110.8">.</w>
    <time id="T144E" value="00:11:34,680" />
  </s>
  <s id="111">
    <time id="T145S" value="00:11:34,681" />
    <w id="111.1">Os</w>
    <w id="111.2">créditos</w>
    <w id="111.3">para</w>
    <w id="111.4">a</w>
    <w id="111.5">Republica</w>
    <w id="111.6">,</w>
    <w id="111.7">estão</w>
    <w id="111.8">nesta</w>
    <w id="111.9">secção</w>
    <time id="T145E" value="00:11:36,921" />
  </s>
  <s id="112">
    <time id="T146S" value="00:12:45,227" />
    <w id="112.1">O</w>
    <w id="112.2">que</w>
    <w id="112.3">é</w>
    <w id="112.4">que</w>
    <w id="112.5">aconteceu</w>
    <w id="112.6">com</w>
    <w id="112.7">as</w>
    <w id="112.8">luzes</w>
    <w id="112.9">?</w>
    <time id="T146E" value="00:12:47,143" />
  </s>
  <s id="113">
    <time id="T147S" value="00:12:47,144" />
    <w id="113.1">Não</w>
    <w id="113.2">consigo</w>
    <w id="113.3">ver</w>
    <w id="113.4">nada</w>
    <w id="113.5">!</w>
    <time id="T147E" value="00:12:48,739" />
  </s>
  <s id="114">
    <time id="T148S" value="00:12:49,856" />
    <w id="114.1">Descobre</w>
    <w id="114.2">o</w>
    <w id="114.3">que</w>
    <w id="114.4">é</w>
    <w id="114.5">que</w>
    <w id="114.6">está</w>
    <w id="114.7">a</w>
    <w id="114.8">acontecer</w>
    <w id="114.9">,</w>
    <w id="114.10">e</w>
    <w id="114.11">abra</w>
    <w id="114.12">o</w>
    <w id="114.13">cofre</w>
    <w id="114.14">imediatamente</w>
    <w id="114.15">!</w>
    <time id="T148E" value="00:12:52,840" />
  </s>
  <s id="115">
    <time id="T149S" value="00:12:53,341" />
    <w id="115.1">A</w>
    <w id="115.2">energia</w>
    <w id="115.3">foi</w>
    <w id="115.4">cortada</w>
    <w id="115.5">...</w>
    <time id="T149E" value="00:12:54,749" />
    <time id="T150S" value="00:12:54,750" />
    <w id="115.6">e</w>
    <w id="115.7">os</w>
    <w id="115.8">procedimentos</w>
    <w id="115.9">de</w>
    <w id="115.10">segurança</w>
    <w id="115.11">foram</w>
    <w id="115.12">accionados</w>
    <w id="115.13">.</w>
    <time id="T150E" value="00:12:56,584" />
  </s>
  <s id="116">
    <time id="T151S" value="00:12:56,585" />
    <w id="116.1">Vai</w>
    <w id="116.2">demorar</w>
    <w id="116.3">algum</w>
    <w id="116.4">tempo</w>
    <w id="116.5">para</w>
    <w id="116.6">os</w>
    <w id="116.7">desligar</w>
    <w id="116.8">.</w>
    <time id="T151E" value="00:12:58,885" />
  </s>
  <s id="117">
    <time id="T152S" value="00:13:28,966" />
    <w id="117.1">-</w>
    <w id="117.2">Onde</w>
    <w id="117.3">é</w>
    <w id="117.4">que</w>
    <w id="117.5">está</w>
    <w id="117.6">a</w>
    <w id="117.7">Senadora</w>
    <w id="117.8">?</w>
  </s>
  <s id="118">
    <w id="118.1">-</w>
    <w id="118.2">Separamo-nos</w>
    <w id="118.3">na</w>
    <w id="118.4">escuridão</w>
    <w id="118.5">.</w>
    <time id="T152E" value="00:13:32,041" />
  </s>
  <s id="119">
    <time id="T153S" value="00:13:32,042" />
    <w id="119.1">Estou</w>
    <w id="119.2">aqui</w>
    <w id="119.3">.</w>
    <time id="T153E" value="00:13:33,641" />
  </s>
  <s id="120">
    <time id="T154S" value="00:13:33,642" />
    <w id="120.1">Não</w>
    <w id="120.2">graças</w>
    <w id="120.3">ao</w>
    <w id="120.4">vosso</w>
    <w id="120.5">sistema</w>
    <w id="120.6">de</w>
    <w id="120.7">segurança</w>
    <w id="120.8">!</w>
    <time id="T154E" value="00:13:35,669" />
  </s>
  <s id="121">
    <time id="T155S" value="00:13:35,670" />
    <w id="121.1">Isto</w>
    <w id="121.2">não</w>
    <w id="121.3">é</w>
    <w id="121.4">o</w>
    <w id="121.5">cofre</w>
    <w id="121.6">,</w>
    <w id="121.7">é</w>
    <w id="121.8">um</w>
    <w id="121.9">túmulo</w>
    <w id="121.10">!</w>
  </s>
  <s id="122">
    <w id="122.1">O</w>
    <w id="122.2">que</w>
    <w id="122.3">é</w>
    <w id="122.4">que</w>
    <w id="122.5">está</w>
    <w id="122.6">a</w>
    <w id="122.7">acontecer</w>
    <w id="122.8">?</w>
    <time id="T155E" value="00:13:39,136" />
  </s>
  <s id="123">
    <time id="T156S" value="00:13:39,137" />
    <w id="123.1">As</w>
    <w id="123.2">minhas</w>
    <w id="123.3">mais</w>
    <w id="123.4">profundas</w>
    <w id="123.5">desculpas</w>
    <w id="123.6">,</w>
    <w id="123.7">Senadora</w>
    <w id="123.8">.</w>
    <time id="T156E" value="00:13:42,390" />
  </s>
  <s id="124">
    <time id="T157S" value="00:13:42,391" />
    <w id="124.1">Parece</w>
    <w id="124.2">que</w>
    <w id="124.3">sou</w>
    <w id="124.4">testemunha</w>
    <w id="124.5">de</w>
    <w id="124.6">muitas</w>
    <w id="124.7">novidades</w>
    <w id="124.8">em</w>
    <w id="124.9">Scipio</w>
    <w id="124.10">.</w>
    <time id="T157E" value="00:13:45,683" />
  </s>
  <s id="125">
    <time id="T158S" value="00:13:45,684" />
    <w id="125.1">Isto</w>
    <w id="125.2">é</w>
    <w id="125.3">um</w>
    <w id="125.4">infeliz</w>
    <w id="125.5">incidente</w>
    <w id="125.6">ou</w>
    <w id="125.7">uma</w>
    <w id="125.8">armadilha</w>
    <w id="125.9">?</w>
    <time id="T158E" value="00:13:48,727" />
  </s>
  <s id="126">
    <time id="T159S" value="00:13:48,728" />
    <w id="126.1">Eu</w>
    <w id="126.2">...</w>
    <w id="126.3">não</w>
    <w id="126.4">tenho</w>
    <w id="126.5">a</w>
    <w id="126.6">certeza</w>
    <w id="126.7">do</w>
    <w id="126.8">que</w>
    <w id="126.9">quer</w>
    <w id="126.10">dizer</w>
    <w id="126.11">com</w>
    <w id="126.12">isso</w>
    <w id="126.13">.</w>
    <time id="T159E" value="00:13:51,729" />
  </s>
  <s id="127">
    <time id="T160S" value="00:13:51,730" />
    <w id="127.1">Receio</w>
    <w id="127.2">que</w>
    <w id="127.3">vou</w>
    <w id="127.4">ter</w>
    <w id="127.5">de</w>
    <w id="127.6">informar</w>
    <w id="127.7">...</w>
    <time id="T160E" value="00:13:53,605" />
    <time id="T161S" value="00:13:53,606" />
    <w id="127.8">sobre</w>
    <w id="127.9">o</w>
    <w id="127.10">lastimável</w>
    <w id="127.11">estado</w>
    <w id="127.12">das</w>
    <w id="127.13">coisas</w>
    <w id="127.14">ao</w>
    <w id="127.15">Chanceler</w>
    <w id="127.16">.</w>
    <time id="T161E" value="00:13:56,282" />
  </s>
  <s id="128">
    <time id="T162S" value="00:14:10,158" />
    <w id="128.1">Vamos</w>
    <w id="128.2">ver</w>
    <w id="128.3">se</w>
    <w id="128.4">conseguiu</w>
    <w id="128.5">o</w>
    <w id="128.6">que</w>
    <w id="128.7">precisávamos</w>
    <w id="128.8">.</w>
    <time id="T162E" value="00:14:12,545" />
  </s>
  <s id="129">
    <time id="T163S" value="00:14:22,084" />
    <w id="129.1">Como</w>
    <w id="129.2">disse</w>
    <w id="129.3">,</w>
    <w id="129.4">os</w>
    <w id="129.5">cofres</w>
    <w id="129.6">estão</w>
    <w id="129.7">vazios</w>
    <w id="129.8">.</w>
    <time id="T163E" value="00:14:25,251" />
  </s>
  <s id="130">
    <time id="T164S" value="00:14:25,252" />
    <w id="130.1">O</w>
    <w id="130.2">Chanceler</w>
    <w id="130.3">tem</w>
    <w id="130.4">de</w>
    <w id="130.5">ver</w>
    <w id="130.6">isto</w>
    <w id="130.7">imediatamente</w>
    <w id="130.8">.</w>
    <time id="T164E" value="00:14:27,879" />
  </s>
  <s id="131">
    <time id="T165S" value="00:14:31,340" />
    <w id="131.1">Senadora</w>
    <w id="131.2">Amidala</w>
    <w id="131.3">,</w>
    <w id="131.4">está</w>
    <w id="131.5">presa</w>
    <w id="131.6">por</w>
    <w id="131.7">espionagem</w>
    <w id="131.8">.</w>
    <time id="T165E" value="00:14:34,967" />
  </s>
  <s id="132">
    <time id="T166S" value="00:14:34,968" />
    <w id="132.1">Não</w>
    <w id="132.2">,</w>
    <w id="132.3">deve</w>
    <w id="132.4">haver</w>
    <w id="132.5">algum</w>
    <w id="132.6">engano</w>
    <w id="132.7">.</w>
    <time id="T166E" value="00:14:36,968" />
  </s>
  <s id="133">
    <time id="T167S" value="00:14:36,969" />
    <w id="133.1">Levem-na</w>
    <w id="133.2">embora</w>
    <w id="133.3">.</w>
    <time id="T167E" value="00:14:39,219" />
  </s>
  <s id="134">
    <time id="T168S" value="00:14:47,018" />
    <w id="134.1">Tenho</w>
    <w id="134.2">amigos</w>
    <w id="134.3">poderosos</w>
    <w id="134.4">.</w>
  </s>
  <s id="135">
    <w id="135.1">O</w>
    <w id="135.2">Chanceler</w>
    <w id="135.3">vai</w>
    <w id="135.4">saber</w>
    <w id="135.5">disto</w>
    <w id="135.6">.</w>
    <time id="T168E" value="00:14:50,326" />
  </s>
  <s id="136">
    <time id="T169S" value="00:15:11,473" />
    <w id="136.1">Por</w>
    <w id="136.2">aqui</w>
    <w id="136.3">,</w>
    <w id="136.4">Mestre</w>
    <w id="136.5">Jedi</w>
    <w id="136.6">.</w>
    <time id="T169E" value="00:15:14,627" />
  </s>
  <s id="137">
    <time id="T170S" value="00:15:19,579" />
    <w id="137.1">Ora</w>
    <w id="137.2">,</w>
    <w id="137.3">ora</w>
    <w id="137.4">,</w>
    <w id="137.5">ora</w>
    <w id="137.6">...</w>
    <time id="T170E" value="00:15:21,129" />
  </s>
  <s id="138">
    <time id="T171S" value="00:15:21,130" />
    <w id="138.1">O</w>
    <w id="138.2">que</w>
    <w id="138.3">é</w>
    <w id="138.4">que</w>
    <w id="138.5">exactamente</w>
    <w id="138.6">está</w>
    <w id="138.7">a</w>
    <w id="138.8">acontecer</w>
    <w id="138.9">aqui</w>
    <w id="138.10">?</w>
    <time id="T171E" value="00:15:23,246" />
  </s>
  <s id="139">
    <time id="T172S" value="00:15:23,247" />
    <w id="139.1">Ani</w>
    <w id="139.2">,</w>
    <w id="139.3">estou</w>
    <w id="139.4">tão</w>
    <w id="139.5">feliz</w>
    <w id="139.6">em</w>
    <w id="139.7">vê-lo</w>
    <w id="139.8">.</w>
    <time id="T172E" value="00:15:26,650" />
  </s>
  <s id="140">
    <time id="T173S" value="00:15:27,826" />
    <w id="140.1">Acho</w>
    <w id="140.2">que</w>
    <w id="140.3">não</w>
    <w id="140.4">sirvo</w>
    <w id="140.5">só</w>
    <w id="140.6">para</w>
    <w id="140.7">travar</w>
    <w id="140.8">guerras</w>
    <w id="140.9">,</w>
    <w id="140.10">afinal</w>
    <w id="140.11">.</w>
    <time id="T173E" value="00:15:30,611" />
  </s>
  <s id="141">
    <time id="T174S" value="00:15:30,612" />
    <w id="141.1">Há</w>
    <w id="141.2">quanto</w>
    <w id="141.3">tempo</w>
    <w id="141.4">é</w>
    <w id="141.5">que</w>
    <w id="141.6">estás</w>
    <w id="141.7">aqui</w>
    <w id="141.8">?</w>
    <time id="T174E" value="00:15:32,654" />
  </s>
  <s id="142">
    <time id="T175S" value="00:15:32,655" />
    <w id="142.1">Há</w>
    <w id="142.2">poucos</w>
    <w id="142.3">dias</w>
    <w id="142.4">.</w>
    <time id="T175E" value="00:15:34,364" />
  </s>
  <s id="143">
    <time id="T176S" value="00:15:34,365" />
    <w id="143.1">Dizem</w>
    <w id="143.2">que</w>
    <w id="143.3">a</w>
    <w id="143.4">Teckla</w>
    <w id="143.5">está</w>
    <w id="143.6">morto</w>
    <w id="143.7">.</w>
    <time id="T176E" value="00:15:36,031" />
  </s>
  <s id="144">
    <time id="T177S" value="00:15:36,032" />
    <w id="144.1">-</w>
    <w id="144.2">É</w>
    <w id="144.3">verdade</w>
    <w id="144.4">?</w>
  </s>
  <s id="145">
    <w id="145.1">-</w>
    <w id="145.2">Sim</w>
    <w id="145.3">.</w>
    <time id="T177E" value="00:15:38,732" />
  </s>
  <s id="146">
    <time id="T178S" value="00:15:38,767" />
    <w id="146.1">Ela</w>
    <w id="146.2">foi</w>
    <w id="146.3">encontrada</w>
    <w id="146.4">atingida</w>
    <w id="146.5">por</w>
    <w id="146.6">um</w>
    <w id="146.7">tiro</w>
    <w id="146.8">no</w>
    <w id="146.9">local</w>
    <w id="146.10">da</w>
    <w id="146.11">bomba</w>
    <w id="146.12">.</w>
    <time id="T178E" value="00:15:40,850" />
  </s>
  <s id="147">
    <time id="T179S" value="00:15:40,851" />
    <w id="147.1">-</w>
    <w id="147.2">Por</w>
    <w id="147.3">quem</w>
    <w id="147.4">?</w>
  </s>
  <s id="148">
    <w id="148.1">-</w>
    <w id="148.2">Não</w>
    <w id="148.3">sabem</w>
    <w id="148.4">.</w>
    <time id="T179E" value="00:15:42,952" />
  </s>
  <s id="149">
    <time id="T180S" value="00:15:42,953" />
    <w id="149.1">Os</w>
    <w id="149.2">Muuns</w>
    <w id="149.3">dizem</w>
    <w id="149.4">que</w>
    <w id="149.5">sabotou</w>
    <w id="149.6">a</w>
    <w id="149.7">rede</w>
    <w id="149.8">eléctrica</w>
    <w id="149.9">.</w>
    <time id="T180E" value="00:15:45,621" />
  </s>
  <s id="150">
    <time id="T181S" value="00:15:45,622" />
    <w id="150.1">O</w>
    <w id="150.2">que</w>
    <w id="150.3">é</w>
    <w id="150.4">que</w>
    <w id="150.5">exactamente</w>
    <w id="150.6">está</w>
    <w id="150.7">a</w>
    <w id="150.8">acontecer</w>
    <w id="150.9">aqui</w>
    <w id="150.10">?</w>
    <time id="T181E" value="00:15:47,539" />
  </s>
  <s id="151">
    <time id="T182S" value="00:15:47,540" />
    <w id="151.1">Tens</w>
    <w id="151.2">de</w>
    <w id="151.3">tirar-me</w>
    <w id="151.4">daqui</w>
    <w id="151.5">.</w>
    <time id="T182E" value="00:15:49,541" />
  </s>
  <s id="152">
    <time id="T183S" value="00:15:49,542" />
    <w id="152.1">-</w>
    <w id="152.2">Clovis</w>
    <w id="152.3">tem</w>
    <w id="152.4">...</w>
  </s>
  <s id="153">
    <w id="153.1">-</w>
    <w id="153.2">O</w>
    <w id="153.3">Clovis</w>
    <w id="153.4">?</w>
  </s>
  <s id="154">
    <w id="154.1">!</w>
    <time id="T183E" value="00:15:51,845" />
  </s>
  <s id="155">
    <time id="T184S" value="00:15:52,627" />
    <w id="155.1">O</w>
    <w id="155.2">que</w>
    <w id="155.3">é</w>
    <w id="155.4">que</w>
    <w id="155.5">o</w>
    <w id="155.6">Clovis</w>
    <w id="155.7">tem</w>
    <w id="155.8">a</w>
    <w id="155.9">ver</w>
    <w id="155.10">com</w>
    <w id="155.11">isto</w>
    <w id="155.12">?</w>
  </s>
  <s id="156">
    <w id="156.1">!</w>
    <time id="T184E" value="00:15:55,126" />
  </s>
  <s id="157">
    <time id="T185S" value="00:15:56,052" />
    <w id="157.1">Não</w>
    <w id="157.2">te</w>
    <w id="157.3">posso</w>
    <w id="157.4">explicar</w>
    <w id="157.5">aqui</w>
    <w id="157.6">.</w>
    <time id="T185E" value="00:15:58,171" />
  </s>
  <s id="158">
    <time id="T186S" value="00:15:58,172" />
    <w id="158.1">Como</w>
    <w id="158.2">é</w>
    <w id="158.3">que</w>
    <w id="158.4">pudeste</w>
    <w id="158.5">confiar</w>
    <w id="158.6">num</w>
    <w id="158.7">homem</w>
    <w id="158.8">como</w>
    <w id="158.9">o</w>
    <w id="158.10">Clovis</w>
    <w id="158.11">...</w>
    <time id="T186E" value="00:16:01,173" />
    <time id="T187S" value="00:16:01,174" />
    <w id="158.12">depois</w>
    <w id="158.13">do</w>
    <w id="158.14">que</w>
    <w id="158.15">ele</w>
    <w id="158.16">fez</w>
    <w id="158.17">?</w>
  </s>
  <s id="159">
    <w id="159.1">!</w>
    <time id="T187E" value="00:16:02,582" />
  </s>
  <s id="160">
    <time id="T188S" value="00:16:02,583" />
    <w id="160.1">É</w>
    <w id="160.2">pela</w>
    <w id="160.3">República</w>
    <w id="160.4">,</w>
    <w id="160.5">Anakin</w>
    <w id="160.6">.</w>
    <time id="T188E" value="00:16:04,759" />
  </s>
  <s id="161">
    <time id="T189S" value="00:16:04,760" />
    <w id="161.1">Alguma</w>
    <w id="161.2">coisa</w>
    <w id="161.3">está</w>
    <w id="161.4">muito</w>
    <w id="161.5">errada</w>
    <w id="161.6">com</w>
    <w id="161.7">os</w>
    <w id="161.8">bancos</w>
    <w id="161.9">.</w>
    <time id="T189E" value="00:16:07,678" />
  </s>
  <s id="162">
    <time id="T190S" value="00:16:07,679" />
    <w id="162.1">Porque</w>
    <w id="162.2">é</w>
    <w id="162.3">que</w>
    <w id="162.4">quando</w>
    <w id="162.5">o</w>
    <w id="162.6">Clovis</w>
    <w id="162.7">está</w>
    <w id="162.8">por</w>
    <w id="162.9">perto</w>
    <w id="162.10">...</w>
    <time id="T190E" value="00:16:09,812" />
    <time id="T191S" value="00:16:09,813" />
    <w id="162.11">as</w>
    <w id="162.12">tuas</w>
    <w id="162.13">desculpas</w>
    <w id="162.14">são</w>
    <w id="162.15">sempre</w>
    <w id="162.16">que</w>
    <w id="162.17">estás</w>
    <w id="162.18">...</w>
    <time id="T191E" value="00:16:11,729" />
  </s>
  <s id="163">
    <time id="T192S" value="00:16:11,730" />
    <w id="163.1">"</w>
    <w id="163.2">a</w>
    <w id="163.3">fazer</w>
    <w id="163.4">alguma</w>
    <w id="163.5">coisa</w>
    <w id="163.6">para</w>
    <w id="163.7">a</w>
    <w id="163.8">República</w>
    <w id="163.9">?</w>
    <w id="163.10">"</w>
    <time id="T192E" value="00:16:13,924" />
  </s>
  <s id="164">
    <time id="T193S" value="00:16:14,725" />
    <w id="164.1">Anakin</w>
    <w id="164.2">,</w>
    <w id="164.3">por</w>
    <w id="164.4">favor</w>
    <w id="164.5">!</w>
    <time id="T193E" value="00:16:16,684" />
  </s>
  <s id="165">
    <time id="T194S" value="00:16:16,685" />
    <w id="165.1">Sabes</w>
    <w id="165.2">,</w>
    <w id="165.3">talvez</w>
    <w id="165.4">te</w>
    <w id="165.5">deixe</w>
    <w id="165.6">aqui</w>
    <w id="165.7">.</w>
    <time id="T194E" value="00:16:19,435" />
  </s>
  <s id="166">
    <time id="T195S" value="00:16:19,436" />
    <w id="166.1">Ani</w>
    <w id="166.2">?</w>
    <time id="T195E" value="00:16:21,186" />
  </s>
  <s id="167">
    <time id="T196S" value="00:16:21,187" />
    <w id="167.1">Já</w>
    <w id="167.2">estás</w>
    <w id="167.3">sob</w>
    <w id="167.4">a</w>
    <w id="167.5">minha</w>
    <w id="167.6">custódia</w>
    <w id="167.7">.</w>
    <time id="T196E" value="00:16:23,187" />
  </s>
  <s id="168">
    <time id="T197S" value="00:16:23,188" />
    <w id="168.1">É</w>
    <w id="168.2">melhor</w>
    <w id="168.3">que</w>
    <w id="168.4">venhas</w>
    <w id="168.5">comigo</w>
    <w id="168.6">antes</w>
    <w id="168.7">que</w>
    <w id="168.8">mude</w>
    <w id="168.9">de</w>
    <w id="168.10">ideias</w>
    <w id="168.11">.</w>
    <time id="T197E" value="00:16:26,315" />
  </s>
  <s id="169">
    <time id="T198S" value="00:16:34,987" />
    <w id="169.1">Anakin</w>
    <w id="169.2">,</w>
    <w id="169.3">por</w>
    <w id="169.4">favor</w>
    <w id="169.5">,</w>
    <w id="169.6">confia</w>
    <w id="169.7">em</w>
    <w id="169.8">mim</w>
    <w id="169.9">.</w>
    <time id="T198E" value="00:16:37,179" />
  </s>
  <s id="170">
    <time id="T199S" value="00:16:37,180" />
    <w id="170.1">Não</w>
    <w id="170.2">posso</w>
    <w id="170.3">ir</w>
    <w id="170.4">sem</w>
    <w id="170.5">os</w>
    <w id="170.6">arquivos</w>
    <w id="170.7">...</w>
    <time id="T199E" value="00:16:39,046" />
    <time id="T200S" value="00:16:39,047" />
    <w id="170.8">que</w>
    <w id="170.9">o</w>
    <w id="170.10">Clovis</w>
    <w id="170.11">e</w>
    <w id="170.12">eu</w>
    <w id="170.13">tiramos</w>
    <w id="170.14">do</w>
    <w id="170.15">cofre</w>
    <w id="170.16">.</w>
    <time id="T200E" value="00:16:41,075" />
  </s>
  <s id="171">
    <time id="T201S" value="00:16:41,076" />
    <w id="171.1">Onde</w>
    <w id="171.2">exactamente</w>
    <w id="171.3">é</w>
    <w id="171.4">que</w>
    <w id="171.5">sugeres</w>
    <w id="171.6">que</w>
    <w id="171.7">procuremos</w>
    <w id="171.8">?</w>
    <time id="T201E" value="00:16:43,618" />
  </s>
  <s id="172">
    <time id="T202S" value="00:16:43,619" />
    <w id="172.1">Os</w>
    <w id="172.2">discos</w>
    <w id="172.3">podem</w>
    <w id="172.4">estar</w>
    <w id="172.5">fora</w>
    <w id="172.6">da</w>
    <w id="172.7">cidade</w>
    <w id="172.8">,</w>
    <time id="T202E" value="00:16:45,536" />
    <time id="T203S" value="00:16:45,537" />
    <w id="172.9">na</w>
    <w id="172.10">residência</w>
    <w id="172.11">particular</w>
    <w id="172.12">do</w>
    <w id="172.13">Clovis</w>
    <w id="172.14">.</w>
    <time id="T203E" value="00:16:47,830" />
  </s>
  <s id="173">
    <time id="T204S" value="00:16:47,831" />
    <w id="173.1">Está</w>
    <w id="173.2">bem</w>
    <w id="173.3">.</w>
  </s>
  <s id="174">
    <w id="174.1">Faço</w>
    <w id="174.2">isso</w>
    <w id="174.3">por</w>
    <w id="174.4">ti</w>
    <w id="174.5">,</w>
    <w id="174.6">não</w>
    <w id="174.7">pelo</w>
    <w id="174.8">Clovis</w>
    <w id="174.9">.</w>
    <time id="T204E" value="00:16:51,582" />
  </s>
  <s id="175">
    <time id="T205S" value="00:16:51,583" />
    <w id="175.1">R-2</w>
    <w id="175.2">...</w>
    <time id="T205E" value="00:16:53,183" />
  </s>
  <s id="176">
    <time id="T206S" value="00:16:54,043" />
    <w id="176.1">Deixe</w>
    <w id="176.2">a</w>
    <w id="176.3">nave</w>
    <w id="176.4">preparada</w>
    <w id="176.5">no</w>
    <w id="176.6">caso</w>
    <w id="176.7">de</w>
    <w id="176.8">precisar</w>
    <w id="176.9">.</w>
    <time id="T206E" value="00:16:56,335" />
  </s>
  <s id="177">
    <time id="T207S" value="00:17:10,596" />
    <w id="177.1">É</w>
    <w id="177.2">mesmo</w>
    <w id="177.3">ali</w>
    <w id="177.4">.</w>
    <time id="T207E" value="00:17:12,197" />
  </s>
  <s id="178">
    <time id="T208S" value="00:17:32,614" />
    <w id="178.1">Lugar</w>
    <w id="178.2">aconchegante</w>
    <w id="178.3">.</w>
    <time id="T208E" value="00:17:34,402" />
  </s>
  <s id="179">
    <time id="T209S" value="00:17:34,403" />
    <w id="179.1">Alguém</w>
    <w id="179.2">esteve</w>
    <w id="179.3">à</w>
    <w id="179.4">procura</w>
    <w id="179.5">dos</w>
    <w id="179.6">ficheiros</w>
    <w id="179.7">.</w>
    <time id="T209E" value="00:17:36,486" />
  </s>
  <s id="180">
    <time id="T210S" value="00:17:36,487" />
    <w id="180.1">Devem</w>
    <w id="180.2">saber</w>
    <w id="180.3">que</w>
    <w id="180.4">o</w>
    <w id="180.5">Clovis</w>
    <w id="180.6">os</w>
    <w id="180.7">tem</w>
    <w id="180.8">.</w>
    <time id="T210E" value="00:17:38,238" />
  </s>
  <s id="181">
    <time id="T211S" value="00:17:38,239" />
    <w id="181.1">Bem</w>
    <w id="181.2">,</w>
    <w id="181.3">talvez</w>
    <w id="181.4">tenham</w>
    <w id="181.5">encontrado</w>
    <w id="181.6">o</w>
    <w id="181.7">que</w>
    <w id="181.8">procuravam</w>
    <w id="181.9">,</w>
    <time id="T211E" value="00:17:40,248" />
    <time id="T212S" value="00:17:40,249" />
    <w id="181.10">e</w>
    <w id="181.11">é</w>
    <w id="181.12">por</w>
    <w id="181.13">isso</w>
    <w id="181.14">que</w>
    <w id="181.15">ele</w>
    <w id="181.16">desapareceu</w>
    <w id="181.17">.</w>
    <time id="T212E" value="00:17:42,131" />
  </s>
  <s id="182">
    <time id="T213S" value="00:17:42,132" />
    <w id="182.1">Só</w>
    <w id="182.2">podemos</w>
    <w id="182.3">ter</w>
    <w id="182.4">esperança</w>
    <w id="182.5">.</w>
    <time id="T213E" value="00:17:43,909" />
  </s>
  <s id="183">
    <time id="T214S" value="00:17:43,910" />
    <w id="183.1">Anakin</w>
    <w id="183.2">,</w>
    <w id="183.3">não</w>
    <w id="183.4">estás</w>
    <w id="183.5">a</w>
    <w id="183.6">ajudar</w>
    <w id="183.7">.</w>
    <time id="T214E" value="00:17:46,018" />
  </s>
  <s id="184">
    <time id="T215S" value="00:17:46,019" />
    <w id="184.1">Não</w>
    <w id="184.2">pareces</w>
    <w id="184.3">entender</w>
    <w id="184.4">o</w>
    <w id="184.5">quão</w>
    <w id="184.6">importante</w>
    <w id="184.7">são</w>
    <w id="184.8">esses</w>
    <w id="184.9">ficheiros</w>
    <w id="184.10">.</w>
    <time id="T215E" value="00:17:49,094" />
  </s>
  <s id="185">
    <time id="T216S" value="00:17:49,095" />
    <w id="185.1">Eles</w>
    <w id="185.2">expõem</w>
    <w id="185.3">a</w>
    <w id="185.4">corrupção</w>
    <w id="185.5">que</w>
    <w id="185.6">existe</w>
    <w id="185.7">no</w>
    <w id="185.8">seio</w>
    <w id="185.9">do</w>
    <w id="185.10">Clã</w>
    <w id="185.11">Bancário</w>
    <w id="185.12">.</w>
    <time id="T216E" value="00:17:53,147" />
  </s>
  <s id="186">
    <time id="T217S" value="00:17:54,099" />
    <w id="186.1">Clovis</w>
    <w id="186.2">!</w>
    <time id="T217E" value="00:17:55,516" />
  </s>
  <s id="187">
    <time id="T218S" value="00:17:55,917" />
    <w id="187.1">Padmé</w>
    <w id="187.2">!</w>
    <time id="T218E" value="00:17:57,598" />
  </s>
  <s id="188">
    <time id="T219S" value="00:17:58,277" />
    <w id="188.1">Sabia</w>
    <w id="188.2">que</w>
    <w id="188.3">virias</w>
    <w id="188.4">.</w>
    <time id="T219E" value="00:17:59,754" />
  </s>
  <s id="189">
    <time id="T220S" value="00:18:02,677" />
    <w id="189.1">Tu</w>
    <w id="189.2">novamente</w>
    <w id="189.3">?</w>
    <time id="T220E" value="00:18:04,124" />
  </s>
  <s id="190">
    <time id="T221S" value="00:18:04,125" />
    <w id="190.1">Sim</w>
    <w id="190.2">,</w>
    <w id="190.3">eu</w>
    <w id="190.4">de</w>
    <w id="190.5">novo</w>
    <w id="190.6">.</w>
    <time id="T221E" value="00:18:06,691" />
  </s>
  <s id="191">
    <time id="T222S" value="00:18:06,692" />
    <w id="191.1">Está</w>
    <w id="191.2">bem</w>
    <w id="191.3">,</w>
    <w id="191.4">galã</w>
    <w id="191.5">,</w>
    <w id="191.6">onde</w>
    <w id="191.7">é</w>
    <w id="191.8">que</w>
    <w id="191.9">estão</w>
    <w id="191.10">os</w>
    <w id="191.11">discos</w>
    <w id="191.12">?</w>
    <time id="T222E" value="00:18:09,621" />
  </s>
  <s id="192">
    <time id="T223S" value="00:18:09,622" />
    <w id="192.1">Não</w>
    <w id="192.2">vou</w>
    <w id="192.3">entregar</w>
    <w id="192.4">a</w>
    <w id="192.5">informação</w>
    <w id="192.6">para</w>
    <w id="192.7">um</w>
    <w id="192.8">piloto</w>
    <w id="192.9">.</w>
    <time id="T223E" value="00:18:12,825" />
  </s>
  <s id="193">
    <time id="T224S" value="00:18:12,826" />
    <w id="193.1">Sou</w>
    <w id="193.2">um</w>
    <w id="193.3">Cavaleiro</w>
    <w id="193.4">Jedi</w>
    <w id="193.5">que</w>
    <w id="193.6">pode</w>
    <w id="193.7">salvar-te</w>
    <w id="193.8">a</w>
    <w id="193.9">vida</w>
    <w id="193.10">...</w>
    <time id="T224E" value="00:18:15,088" />
    <time id="T225S" value="00:18:15,089" />
    <w id="193.11">se</w>
    <w id="193.12">me</w>
    <w id="193.13">entregares</w>
    <w id="193.14">os</w>
    <w id="193.15">ficheiros</w>
    <w id="193.16">.</w>
    <time id="T225E" value="00:18:16,989" />
  </s>
  <s id="194">
    <time id="T226S" value="00:18:16,990" />
    <w id="194.1">Então</w>
    <w id="194.2">,</w>
    <w id="194.3">como</w>
    <w id="194.4">é</w>
    <w id="194.5">que</w>
    <w id="194.6">vai</w>
    <w id="194.7">ser</w>
    <w id="194.8">?</w>
    <time id="T226E" value="00:18:19,662" />
  </s>
  <s id="195">
    <time id="T227S" value="00:18:19,663" />
    <w id="195.1">Vais</w>
    <w id="195.2">dar-me</w>
    <w id="195.3">os</w>
    <w id="195.4">discos</w>
    <w id="195.5">?</w>
    <time id="T227E" value="00:18:20,964" />
  </s>
  <s id="196">
    <time id="T228S" value="00:18:20,965" />
    <w id="196.1">Para</w>
    <w id="196.2">me</w>
    <w id="196.3">abandonares</w>
    <w id="196.4">como</w>
    <w id="196.5">da</w>
    <w id="196.6">última</w>
    <w id="196.7">vez</w>
    <w id="196.8">?</w>
    <time id="T228E" value="00:18:23,899" />
  </s>
  <s id="197">
    <time id="T229S" value="00:18:23,900" />
    <w id="197.1">Isso</w>
    <w id="197.2">depende</w>
    <w id="197.3">do</w>
    <w id="197.4">quão</w>
    <w id="197.5">bem</w>
    <w id="197.6">comportado</w>
    <w id="197.7">fores</w>
    <w id="197.8">.</w>
    <time id="T229E" value="00:18:26,250" />
  </s>
  <s id="198">
    <time id="T230S" value="00:18:26,251" />
    <w id="198.1">Podem</w>
    <w id="198.2">parar</w>
    <w id="198.3">de</w>
    <w id="198.4">discutir</w>
    <w id="198.5">para</w>
    <w id="198.6">que</w>
    <w id="198.7">possamos</w>
    <w id="198.8">sair</w>
    <w id="198.9">daqui</w>
    <w id="198.10">?</w>
    <time id="T230E" value="00:18:29,844" />
  </s>
  <s id="199">
    <time id="T231S" value="00:18:38,858" />
    <w id="199.1">Abaixem-se</w>
    <w id="199.2">!</w>
    <time id="T231E" value="00:18:40,160" />
  </s>
  <s id="200">
    <time id="T232S" value="00:18:43,718" />
    <w id="200.1">-</w>
    <w id="200.2">Obrigado</w>
    <w id="200.3">.</w>
  </s>
  <s id="201">
    <w id="201.1">-</w>
    <w id="201.2">Não</w>
    <w id="201.3">tentei</w>
    <w id="201.4">salvar-te</w>
    <w id="201.5">a</w>
    <w id="201.6">ti</w>
    <w id="201.7">.</w>
    <time id="T232E" value="00:18:46,816" />
  </s>
  <s id="202">
    <time id="T233S" value="00:18:46,817" />
    <w id="202.1">Anakin</w>
    <w id="202.2">,</w>
    <w id="202.3">tira-nos</w>
    <w id="202.4">daqui</w>
    <w id="202.5">.</w>
    <time id="T233E" value="00:18:48,958" />
  </s>
  <s id="203">
    <time id="T234S" value="00:18:48,959" />
    <w id="203.1">Sigam-me</w>
    <w id="203.2">.</w>
    <time id="T234E" value="00:18:50,261" />
  </s>
  <s id="204">
    <time id="T235S" value="00:18:51,512" />
    <w id="204.1">Corram</w>
    <w id="204.2">!</w>
    <time id="T235E" value="00:18:52,812" />
  </s>
  <s id="205">
    <time id="T236S" value="00:19:26,194" />
    <w id="205.1">R2</w>
    <w id="205.2">,</w>
    <w id="205.3">traz</w>
    <w id="205.4">a</w>
    <w id="205.5">nave</w>
    <w id="205.6">aqui</w>
    <w id="205.7">para</w>
    <w id="205.8">nos</w>
    <w id="205.9">apanhares</w>
    <w id="205.10">.</w>
    <time id="T236E" value="00:19:29,230" />
  </s>
  <s id="206">
    <time id="T237S" value="00:20:09,260" />
    <w id="206.1">Cuidado</w>
    <w id="206.2">!</w>
    <time id="T237E" value="00:20:10,563" />
  </s>
  <s id="207">
    <time id="T238S" value="00:20:11,115" />
    <w id="207.1">Anakin</w>
    <w id="207.2">!</w>
    <time id="T238E" value="00:20:12,417" />
  </s>
  <s id="208">
    <time id="T239S" value="00:20:21,958" />
    <w id="208.1">Despistamo-lo</w>
    <w id="208.2">?</w>
    <time id="T239E" value="00:20:23,406" />
  </s>
  <s id="209">
    <time id="T240S" value="00:20:30,185" />
    <w id="209.1">Estou</w>
    <w id="209.2">bem</w>
    <w id="209.3">.</w>
    <time id="T240E" value="00:20:31,487" />
  </s>
  <s id="210">
    <time id="T241S" value="00:20:42,149" />
    <w id="210.1">R2</w>
    <w id="210.2">,</w>
    <w id="210.3">aproxima-te</w>
    <w id="210.4">ao</w>
    <w id="210.5">meu</w>
    <w id="210.6">sinal</w>
    <w id="210.7">.</w>
  </s>
  <s id="211">
    <w id="211.1">R2</w>
    <w id="211.2">?</w>
    <time id="T241E" value="00:20:45,067" />
  </s>
  <s id="212">
    <time id="T242S" value="00:20:53,916" />
    <w id="212.1">Bem</w>
    <w id="212.2">apanhado</w>
    <w id="212.3">!</w>
    <time id="T242E" value="00:20:55,218" />
  </s>
  <s id="213">
    <time id="T243S" value="00:21:14,676" />
    <w id="213.1">Gudtak</w>
    <w id="213.2">Marrok</w>
    <w id="213.3">.</w>
    <time id="T243E" value="00:21:16,807" />
  </s>
  <s id="214">
    <time id="T244S" value="00:21:17,702" />
    <w id="214.1">Que</w>
    <w id="214.2">passkuna</w>
    <w id="214.3">Bestiole-li</w>
    <w id="214.4">!</w>
    <time id="T244E" value="00:21:20,862" />
  </s>
  <s id="215">
    <time id="T245S" value="00:21:20,863" />
    <w id="215.1">Parece</w>
    <w id="215.2">que</w>
    <w id="215.3">a</w>
    <w id="215.4">tua</w>
    <w id="215.5">missão</w>
    <w id="215.6">foi</w>
    <w id="215.7">um</w>
    <w id="215.8">sucesso</w>
    <w id="215.9">...</w>
    <time id="T245E" value="00:21:23,400" />
  </s>
  <s id="216">
    <time id="T246S" value="00:21:23,401" />
    <w id="216.1">Caçador</w>
    <w id="216.2">de</w>
    <w id="216.3">Recompensas</w>
    <w id="216.4">.</w>
    <time id="T246E" value="00:21:24,876" />
  </s>
  <s id="217">
    <time id="T247S" value="00:21:24,877" />
    <w id="217.1">Daqui</w>
    <w id="217.2">para</w>
    <w id="217.3">a</w>
    <w id="217.4">frente</w>
    <w id="217.5">,</w>
    <w id="217.6">eu</w>
    <w id="217.7">mesmo</w>
    <w id="217.8">trato</w>
    <w id="217.9">deles</w>
    <w id="217.10">.</w>
    <time id="T247E" value="00:21:28,886" />
  </s>
  <s id="218">
    <time id="T248S" value="00:21:38,377" />
    <w id="218.1">Tradução</w>
    <w id="218.2">PtBr</w>
    <w id="218.3">Tozz</w>
    <w id="218.4">,</w>
    <w id="218.5">Dres</w>
    <w id="218.6">,</w>
    <w id="218.7">Helder</w>
    <w id="218.8">,</w>
    <w id="218.9">Sardinha</w>
    <w id="218.10">Adaptação</w>
    <w id="218.11">PtPt</w>
  </s>
  <s id="219">
    <w id="219.1">-</w>
    <w id="219.2">Arodri</w>
    <time id="T248E" value="00:21:42,886" />
  </s>
  <s id="220">
    <time id="T249S" value="00:21:42,977" />
    <w id="220.1">Sincronização</w>
    <w id="220.2">:</w>
  </s>
  <s id="221">
    <w id="221.1">NeoStar</w>
    <time id="T249E" value="00:21:46,886" />
  </s>
  <meta>
    <source>
      <duration>23</duration>
      <year>2014</year>
      <genre>Action,Adventure,Animation</genre>
    </source>
    <conversion>
      <sentences>221</sentences>
      <tokens>1855</tokens>
      <encoding>windows-1252</encoding>
      <unknown_words>14</unknown_words>
      <ignored_blocks>0</ignored_blocks>
      <corrected_words>0</corrected_words>
      <truecased_words>6</truecased_words>
    </conversion>
    <subtitle>
      <date>2015-08-07</date>
      <cds>1/1</cds>
      <duration>00:21:46,886</duration>
      <language>Portuguese</language>
      <confidence>1.0</confidence>
      <blocks>249</blocks>
    </subtitle>
  </meta>
</document>
