{"line 1": "UM ORIGINAL NETFLIX Está muito bom ", "line 2": "Hendrix, que grande jantar ", "line 3": "Acho que tenho de desapertar um botão ", "line 4": "- Era recheio de queijo creme ? - Não sei ", "line 5": "Será ? - Tu és malvada, Alison Hendrix ", "line 6": "- Eu mando te a receita por e-mail ", "line 7": "- Não mandas ", "line 8": "- Ela é tão rígida ", "line 9": "- Estou ? - Olá, Alison ", "line 10": "É a Beth ", "line 11": "Eu disse te para não voltares a ligar ", "line 12": "Tu sabes que ignorar isto não vai fazê lo desaparecer ", "line 13": "Eu avisei te quando em os conhecemos ", "line 14": "Beth, nós somos parecidas, mais nada ", "line 15": "Essa coisa começada por \"C \", nem sei o que dizer sobre isso ", "line 16": "É um disparate, entendes ? Alison ? Sim, ótimo ", "line 17": "Vendidas ", "line 18": "Rifas vendidas ", "line 19": "Boa ", "line 20": "Certo ", "line 21": "Adeus ", "line 22": "Tu estiveste agarrada a o telefone a noite inteira ", "line 23": "- Andas a esconder alguma coisa ? - O quê ? Malta, eu e a Aynsley temos uma proposta para vocês ", "line 24": "Estivemos a pensar e está em a hora de agitar um pouco as águas ", "line 25": "- Não ", "line 26": "- Meu Deus ", "line 27": "- Não, não, nada de isso ", "line 28": "Não, não ", "line 29": "- O que estávamos a pensar era um pouco de ", "line 30": "Cogumelos mágicos ", "line 31": "Eu não posso ", "line 32": "Experimentei uma vez e deram me a volta a a barriga ", "line 33": "- Donnie, vá lá ", "line 34": "- Não ", "line 35": "Eu e a Alison preferimos álcool ", "line 36": "QUERO QUE CONHEÇAS UMA PESSOA Está tudo bem, querida ? - Sim ", "line 37": "Porque não abrimos um Merlot ? - Sabem que mais ? Vamos a isso ", "line 38": "- Sim ", "line 39": "Assim é que se fala, Hendrix ", "line 40": "Bate aqui ", "line 41": "- Tens a certeza de isto ? - Ela está em negação ", "line 42": "Precisa de ver mais uma ", "line 43": "Sim, mas tu estás a pedir me que largue uma bomba em o meio de um quadro de Norman Rockwell ", "line 44": "Sim ", "line 45": "Avança ", "line 46": "Está bem ", "line 47": "Nós precisamos de a localização de a Helena e vocês vão dizer me ", "line 48": "- Para onde foi ela, ", "line 49": "Hendrix ? - Já lhe disse que não sei ", "line 50": "Abandonou te, não foi ? Como me abandonaste em a floresta ", "line 51": "Eu não te abandonei, Alison ", "line 52": "- Ouça, ", "line 53": "- Frontenac ", "line 54": "Certo ", "line 55": "Diga a a Rachel que quando me encontrou eu andava a a procura de a Helena ", "line 56": "- Não, diga a a Rachel que a Helena não vai deixá la tirar células estaminais de os bebés ", "line 57": "Não é exatamente cientista, pois não, Sra ", "line 58": "Hendrix ? Eu estudei cinesiologia ", "line 59": "A Cosima é uma verdadeira cientista e muito valiosa ", "line 60": "A Sarah e a Helena são férteis ", "line 61": "São biologicamente valiosas ", "line 62": "E depois temos a Alison ", "line 63": "Eu sou mãe e dona de casa ", "line 64": "Quando voltar a a sua existência inútil, quero que considere o seu valor, porque até a ", "line 65": "tinha mais valor de o que a Alison ", "line 66": "A minha mão é roxa e distorce o ar ", "line 67": "Estou a ver rastos ", "line 68": "Porque é que as minhas meias estão molhadas ? Muito bem ", "line 69": "Água fresca para todos ", "line 70": "Sim, tem gelo e tudo ", "line 71": "E tenho a linha de controlo de venenos em ligação direta ", "line 72": "Donnie, bebe uma cerveja ", "line 73": "Tira a camisa ", "line 74": "O quê ? Não ", "line 75": "É o homem mistério de a Alison outra vez ", "line 76": "- O quê ? - Não, não, não ", "line 77": "Querida, não achas melhor desligar isso ? ISTO É REAL ", "line 78": "VAI LÁ FORA ", "line 79": "Tenho de ir buscar as rifas ", "line 80": "- Espera ", "line 81": "- Dá cá mais cinco ", "line 82": "- E o sistema de o amigo ? - Eu estou bem ", "line 83": "Está bem ", "line 84": "Alison ", "line 85": "Olá ", "line 86": "- Céus ", "line 87": "Eu tenho vizinhos ", "line 88": "- Eu sei ", "line 89": "Desculpa ", "line 90": "- Tu és a outra ", "line 91": "- Sim, sou a Cosima ", "line 92": "Eu sei ", "line 93": "Desculpa a emboscada ", "line 94": "Foi ideia de a Beth ", "line 95": "Ela pensou que fosse boa ideia veres mais uma de nós ", "line 96": "Tu tens um brinco em o nariz ", "line 97": "Sim, uma observação brilhante ", "line 98": "- Nós somos tão diferentes ", "line 99": "- Eu sei, o que pode parecer estranho, mas para mim é tão fascinante ", "line 100": "Esta és tu e eu sou de Berkeley ", "line 101": "Entendes ? - Nem sequer sei o que isso significa ", "line 102": "- E tipo, a Beth é polícia ", "line 103": "Certo ? Mas geneticamente somos todas de a mesma família ", "line 104": "Quem somos nós em a verdade ? Sim, essa é a questão existencial, não é ? Mas a proposta de a Beth é que em os juntemos todas, que andemos juntas ", "line 105": "Tu vais ter con nosco e conversamos ", "line 106": "- Vamos falar e falar ", "line 107": "- Não ", "line 108": "Tu estás pedrada ? Porque os teus olhos estão a brilhar ", "line 109": "- Não com si lidar com isto agora ", "line 110": "- Ali ", "line 111": "Muito bem ", "line 112": "Merda ", "line 113": "", "line 114": "", "line 115": "Eu podia ter feito alguma coisa, Sarah ", "line 116": "- Podia ter sido isco ", "line 117": "- Eles também estavam a vigiar te ", "line 118": "Acho que devemos recolher nos ", "line 119": "Juntar nos ", "line 120": "- Parece me boa ideia ", "line 121": "- Sim ", "line 122": "Vou voltar a a minha vida inútil, como me foi dito ", "line 123": "Querida ? Querida ? Kira ? Queres dar me ", "line 124": "Ela precisa de espaço ", "line 125": "E tu também ", "line 126": "Eu levo a a a Dyad ", "line 127": "Ela não me diz o que a Rachel lhe fez e eu tenho de mandá la para lá ", "line 128": "Eu sei que não é fácil, mas continua a acreditar ", "line 129": "Nós temos aliados ", "line 130": "Fica aqui ", "line 131": "Acorrenta te a a tua irmã hoje ", "line 132": "Donnie, não me apetece ir a a Feira de Outono, não com a Nona Walker responsável ", "line 133": "Continuamos a ter o entretenimento ", "line 134": "Eu vou dançar e nós vamos cantar em dueto, certo ? Não há montanha alta o suficiente Não há vale ", "line 135": "Pronto, querida, vá lá ", "line 136": "O que é a Feira de Outono sem a Equipa Hendrix ? Não com si deixar de pensar em a ", "line 137": "e em a Cosima, lá sozinha ", "line 138": "Porque é que eu amo tanto as minhas irmãs quando elas destruíram a minha vida ? - A tua vida não está destruída ", "line 139": "Só está a a espera que tu voltes e lhe dês brilho ", "line 140": "Tens razão ", "line 141": "Tens razão ", "line 142": "Eu fiz de esta feira o que ela é hoje e não vou ser posta de parte por a Nona Walker ", "line 143": "- Não era isso ", "line 144": "- Veste te ", "line 145": "Engalanado ", "line 146": "Eu estou em a igreja ", "line 147": "FEIRA ANUAL DE OUTONO TODOS SÃO BEM-VINDOS - Olá ", "line 148": "- Olá ", "line 149": "Vamos pôr as bebidas em a mesa de as sobremesas ", "line 150": "- Ali ? - Ou talvez com os acompanhamentos ", "line 151": "Desculpa ", "line 152": "Sei que é pesado ", "line 153": "Parece te bem ? Acompanhamentos ? As bebidas ficam sempre em uma mesa separada ", "line 154": "Assim evitamos acidentes ", "line 155": "Ótimo ", "line 156": "Alison, chegaste cedo ", "line 157": "A feira só começa de aqui a uma hora ", "line 158": "Bem, pode não começar, por este andar ", "line 159": "- Em que pé estamos ? - Vamos respirar fundo, querida ", "line 160": "- Está bem ? - Desculpe ? Disseram me que podias tentar fazer isto ", "line 161": "Tentar minar me ", "line 162": "- Quem disse isso ? - A Eileen, a Nina, a Nancy e a Sta ", "line 163": "Bem, toda a gente ", "line 164": "E eu disse que não, que a Alison não é assim ", "line 165": "Para teu bem, vamos provar que eles estão errados, está bem ? - Está bem ", "line 166": "- Ótimo ", "line 167": "Talvez em o próximo ano, Alison ", "line 168": "Essa vai para a mesa de os cachorros-quentes ", "line 169": "- Nona ", "line 170": "- Alison, ainda estás aqui ", "line 171": "Eu queria pedir lhe desculpa ", "line 172": "Não tenho estado em mim ultimamente ", "line 173": "A minha família e a minha reputação ", "line 174": "Já sabe ", "line 175": "Sinto me um pouco inútil ", "line 176": "- Céus ", "line 177": "- Deve estar com sede ", "line 178": "Está a trabalhar muito ", "line 179": "Beba qualquer coisa ", "line 180": "- Que atenciosa ", "line 181": "Obrigada ", "line 182": "- Tudo bem ", "line 183": "Alison ", "line 184": "Bem-vinda ", "line 185": "Espero que não tenhas ficado triste com a mudança de liderança ", "line 186": "Não ", "line 187": "Eu e a Nona já resolvemos tudo ", "line 188": "Graças a Deus ", "line 189": "Ele vê as tuas ações, pequenas e grandes ", "line 190": "Podes procurar consolar em isso ", "line 191": "Eu acabei de perceber que tenho isto em o carro há semanas ", "line 192": "As parafinas matavam na ", "line 193": "Vou buscar lhe outra ", "line 194": "O Aldous ficou tão orgulhoso quando publicou este livro, mas o ", "line 195": "Westmorland disse me que o tinha escrito e que o Aldous só o apalermou ", "line 196": "- Não sabia de isso ", "line 197": "A imagem mostra que o feto teve uma recuperação rápida e inexplicável ", "line 198": "Sim, os filhos de a Helena podem ser ainda mais importantes de o que a Kira ", "line 199": "O Donnie Hendrix pode estar a esconder onde está a Helena ", "line 200": "Temos vantagem persuasiva, certo ? Vou dar instruções a os Inspetores ", "line 201": "- Inspetor Bell, o que é que se passa ? - Diz me tu ", "line 202": "Vou fazer uma dança escocesa mais logo ", "line 203": "Quebra a minha liberdade condicional ? Temos um mandado de busca ", "line 204": "Porquê ? Já fui acusado ", "line 205": "Não é por causa de o tráfico de droga, Donnie ", "line 206": "É um montede bandidos portugueses mortos e uma guilhotina de papel ensanguentada ", "line 207": "Vá lá ", "line 208": "- Isto é chantagem ", "line 209": "- Sai de a frente, \" Braveheart \" ", "line 210": "Alison, o que é que estás a fazer aqui ? Estou a adorar os meus vizinhos, Eileen ", "line 211": "Tenta não julgar ", "line 212": "- Todos temos saudades de ela ", "line 213": "- Olá, Chad ", "line 214": "Olá, Jake ", "line 215": "Olá, Esmea ", "line 216": "Não vos vejo desde ", "line 217": "- O funeral ", "line 218": "Sim ", "line 219": "- Sim, sim ", "line 220": "Lamento muito ", "line 221": "Sentimos a vossa falta em Black Oak Drive ", "line 222": "Agora vivemos em a casa de a mãe de a Aynsley ", "line 223": "Estou preocupado em tomar conta de os meus VIP ", "line 224": "Não é ? Sim ", "line 225": "- Vamos buscar os cachorros-quentes ", "line 226": "- Está bem ", "line 227": "- Ela era mesmo bonita, não era ? - Sim ", "line 228": "Nunca pensaste que de certa forma foi culpa nossa ? De o que é que estás a falar ? Foi um acidente ", "line 229": "Ela expulsou me de casa porque tivemos um caso ", "line 230": "Se estivesse alguém em casa, podia tê la salvo ", "line 231": "Não sabes isso e não podemos mudar o passado ", "line 232": "Sim ", "line 233": "Gostei de te ver, Alison ", "line 234": "Porque é que eu tenho esta cara ? Podia ter nascido com muitas caras ", "line 235": "Podia ter sido polícia ou cientista, mas acabei a fazer minipizas em o micro-ondas e a levar miúdos a o circo ", "line 236": "Porquê esta vida ? Porque somos felizes ? Tu és tão normal ", "line 237": "Tu jogas golfe, vês televisão e vais para o trabalho ", "line 238": "Mas por vezes olhas para mim de uma forma tão estranha ", "line 239": "É como se a nossa vida fosse uma mentira ", "line 240": "Eu pesquisei \" má trip de cogumelos mágicos \" e dizia que de aqui a duas horas voltas a o normal ", "line 241": "Está bem ? Está bem ", "line 242": "- Meu Deus ", "line 243": "- Má energia aqui ", "line 244": "- Malta, a Alison não está bem ", "line 245": "- Querida, não ", "line 246": "São só os teus sentidos a abrir como uma flor ", "line 247": "- Eu não me sinto uma flor ", "line 248": "- Não querida ", "line 249": "Anda lá para fora ", "line 250": "Anda sentir a relva ", "line 251": "É tão bonita ", "line 252": "- Sim ", "line 253": "- Sim ", "line 254": "Tenham cuidado com ela ", "line 255": "Já disse centenas de vezes ", "line 256": "Não sei onde está a Helena ", "line 257": "Há alguma coisa aqui ? Pornografia infantil ? Fuga a os impostos ? A lista de clientes de o Pouchy ? Não ", "line 258": "Tenho de ligar a a minha mulher ", "line 259": "- Também preciso de esse telemóvel ", "line 260": "- Estás a apoiar esta farsa ? Donnie ", "line 261": "Por favor ", "line 262": "Estão a a minha espera em o palco de a Feira de Outono ", "line 263": "Vai e dança com as estrelas ", "line 264": "Não há nenhuma lei que diga que tens de ficar em casa ", "line 265": "- Está tudo bem, Donnie ? - Sim, estamos bem ", "line 266": "Mas não os deixes aproximarem se de a garagem ", "line 267": "Lembras te de o teu acidente de automóvel, Kira ? Sim ", "line 268": "A Miss S disse que era um milagre ", "line 269": "E se eu te disser que pode não ser um milagre ", "line 270": "Pode ser alguma coisa presente em os teus genes ", "line 271": "- É o que a tia Cosima pensa ", "line 272": "- Pensa sim ", "line 273": "Tenho um presente para ti ", "line 274": "Mais uma criatura muito especial ", "line 275": "Um rato ", "line 276": "É um acomys dimidiatus ", "line 277": "Este rato tem a capacidade incrível de regenerar a pele e o por o ", "line 278": "- Como ? - Isso é um mistério ", "line 279": "Posso pegar em ele ? Claro ", "line 280": "Evoluiu de esta forma para que, quando apanhado por um predador, consiga sair de a sua pele e fugir ", "line 281": "- Vá lá ", "line 282": "Julgo que é indolor ", "line 283": "Toda a gente diz que não posso confiar em ti ", "line 284": "Confias ? Isto é engraçado ", "line 285": "A Kira já se está a voltar contra mim ", "line 286": "Ela acha que a Rachel lhe vai explicar que é e eu sou a bruxa má que diz \" não \" ", "line 287": "Não ", "line 288": "Sim ", "line 289": "Rabo em a cadeira ", "line 290": "Tu vais posar para mim ", "line 291": "- Não vou posar para ti ", "line 292": "- Sim, vais posar para mim, a ", "line 293": "pôs nos de castigo e sei que isso é terrível para ti, por isso, vamos fazer qualquer coisa construtiva ", "line 294": "- Porque é que insistes em pintar nu ? - É o meu método ", "line 295": "E tu não tens nada com isso, por isso, descontrai ", "line 296": "Olhos a olhar para a frente ", "line 297": "Boa ", "line 298": "Sê natural ", "line 299": "- Ramone ", "line 300": "Tu enganaste nos ", "line 301": "- Sra ", "line 302": "Hendrix ", "line 303": "O Kellerman deu nos aqueles comprimidos e tu deixaste nos pendurados ", "line 304": "O quê ? Isso não é verdade ", "line 305": "O produto foi comprado e pago ", "line 306": "Tu ", "line 307": "De esta vez não me vais enganar ", "line 308": "Quero os meus 35 mil ", "line 309": "Calma lá ", "line 310": "Acha que vinha aqui, a a sua igreja, se a tivesse enganado ? Considere a possibilidade de o Kellerman a ter considerado uma novata e ter se aproveitado de si ", "line 311": "- Fomos enganados ", "line 312": "- Ele é uma cobra ", "line 313": "- Eu devia tê la avisado ", "line 314": "- Sou um fracasso colossal em tudo ", "line 315": "Para mim não é, Sra ", "line 316": "Hendrix ", "line 317": "- Posso ajudá la a esquecer ? - Não, claro que não ", "line 318": "Céus ", "line 319": "Não bebo há séculos ", "line 320": "A mulher que eu era há um ano não reconheceria a mulher que sou hoje ", "line 321": "- Quem és tu ? - Sim ", "line 322": "Agora sou o tipo que fornece as festas ", "line 323": "Voltei a viver em a cave de os meus pais ", "line 324": "Promete me que não acabas em Bailey Downs de aqui a dez anos a perguntar o que aconteceu a a tua vida ", "line 325": "Um bafo, Sra ", "line 326": "Hendrix ? Que se lixe ", "line 327": "Olha para as estrelas ", "line 328": "Algumas estão tão longe que morreram antes de a luz chegar aqui ", "line 329": "Aynsley, achas que isto é tudo o que está guardado para nós ? Bailey Downs ? - Estás a rir te de mim ? - Não, não querida ", "line 330": "Eu compreendo te ", "line 331": "A as vezes penso saltar para o carro e fugir ", "line 332": "Quem sabe o que há lá fora a a minha espera ? Exatamente ", "line 333": "Mas Ali, este bairro é ótimo ", "line 334": "As nossas vidas estão cheias de alegria, filhos e churrascos ", "line 335": "Mas se achas que há outra coisa guardada para ti, deves confiar em isso ", "line 336": "Sra ", "line 337": "Hendrix ", "line 338": "Alison, o que estás a fazer ? Donnie, estou altamente ", "line 339": "Quer dizer, estou ", "line 340": "- Estou tão pedrada, Donnie ", "line 341": "- Esse é o Ramone ? Seu merdoso ", "line 342": "Sr ", "line 343": "Hendrix, eu juro que não o enganei ", "line 344": "Eu juro ", "line 345": "- Foi o Kellerman de o olhar distante ", "line 346": "- Alison, anda cá ", "line 347": "- Fala para a mão saltitante, Donnie ", "line 348": "- Alison, podes vir aqui ? Sim, despacha te ", "line 349": "Agora é a minha vez ! Está bem ", "line 350": "Teste de segurança terminado ", "line 351": "Qual é o teu problema, Donnie ? O meu problema ? Não sei ", "line 352": "Polícias Neo a revistar a nossa casa ", "line 353": "- O quê ? A polícia ? - Sim ", "line 354": "- Porquê ? - Estão a tentar ligar nos a o Pouchy ? Não há provas que em os liguem a o Pouchy, pois não ? Não, mas há alguns corpos enterrados em a nossa garagem ", "line 355": "O que acontece quando a Rachel descobrir que eu matei o Leekie ? Não lhe dei um tiro em a cabeça, pois não ? Não, só deixaste a Aynsley Norris sufocar até a a morte ", "line 356": "Pensava que ela era a minha monitora ", "line 357": "E afinal eras tu ", "line 358": "Não me orgulho de o que fiz ", "line 359": "Enger ? Merda ", "line 360": "A deixar provas ? Isso é sangue de a cena de o crime de o Pouchy ? Sim, roupa ensanguentada ", "line 361": "Sabes que os Hendrixes não o fizeram, Matty ", "line 362": "A ironia é essa ", "line 363": "Acho que ambos sabemos quem foi ", "line 364": "A Helena ", "line 365": "Também juntei sangue de o clone ", "line 366": "Ligamos a mulher a o crime e o marido diz nos onde está a Helena ", "line 367": "Parece uma sepultura, não parece ? Sim, senhora ", "line 368": "Vou tratar de o assunto ", "line 369": "A Alison ? Alison ? - É o Donnie ", "line 370": "- Donnie, o que é que se passa ? Estou em a feira de a igreja, a Alison está embriagada e a polícia está a revistar a minha casa ", "line 371": "- O Art está lá ? - Sim, estava ", "line 372": "Não sei se consegue, disse lhe para os manter longe de a garagem, com os seus ocupantes ", "line 373": "- Merda ", "line 374": "O Leekie ", "line 375": "E o Castor morto de a Helena ", "line 376": "Não te esqueças de ele ", "line 377": "Donnie, estás a dizer que a Alison voltou a consumir ? Sim ", "line 378": "Com o traficante adolescente ", "line 379": "A ", "line 380": "que se lixe ", "line 381": "Eles precisam de ajuda ", "line 382": "- Temos de ir ", "line 383": "- Espera ", "line 384": "Estamos a ir ", "line 385": "Está bem ", "line 386": "Obrigado ", "line 387": "Que bom ", "line 388": "- Trabalhos de casa, minha menina ? - Estão feitos ", "line 389": "- Impressionante ", "line 390": "- A que horas a mãe chega a casa ? Não tarda, espero eu ", "line 391": "Ela disse que já estaria em casa a esta hora ", "line 392": "Eu sei ", "line 393": "Queres falar sobre o que tu e a Rachel fizeram hoje ? Não ", "line 394": "- Está bem ", "line 395": "Prepara te para dormir ", "line 396": "- Está bem ", "line 397": "Alison ? Olá, Chad ", "line 398": "- Posso sentar me ? - Claro ", "line 399": "Antes chamavas me Hendrix ", "line 400": "Sim ", "line 401": "Sim, antes fazia muitas coisas ", "line 402": "Estás bem ? Não ", "line 403": "Há uma coisa que devia ter te contado sobre a morte de a Aynsley ", "line 404": "- Ouve, Ali, não tens de dizer nada ", "line 405": "- Não, tens de me ouvir ", "line 406": "A culpa foi minha ", "line 407": "Eu sou a responsável ", "line 408": "Não ", "line 409": "Eu não devia ter dito nada ", "line 410": "Desculpa ", "line 411": "Foi estúpido ", "line 412": "Vocês tinham os vossos problemas, mas eram problemas de melhores amigas ", "line 413": "Ela adorava te ", "line 414": "Ela adorava te a sério ", "line 415": "Não podemos mudar o que aconteceu ", "line 416": "Mas se queremos honrar a Aynsley, temos de continuar ", "line 417": "Obrigada ", "line 418": "É melhor ir a a procura de o Donnie antes que perca a atuação ", "line 419": "Donnie ", "line 420": "Até os mais estranhos têm um ", "line 421": "Céus ", "line 422": "Donnie ! Donnie ", "line 423": "Céus ", "line 424": "Donnie, acorda ", "line 425": "Acorda ", "line 426": "Eu estou aqui ", "line 427": "Eu estou aqui ", "line 428": "Acorda ", "line 429": "Acorda, Donnie ", "line 430": "Levanta te ", "line 431": "Felix ", "line 432": "Sim, mesmo a tempo ", "line 433": "O que é que ele tomou ? - Metade de um frasco de Lorazepam ", "line 434": "- Merda ", "line 435": "- Ele está bem ? - Sim ", "line 436": "Ele está ótimo, mas tem estado doente ", "line 437": "Parece que são os dois alcoólicos ", "line 438": "Desculpe ", "line 439": "Eu posso ter os meus demónios, mas não se atreva a falar de o meu Donnie ", "line 440": "Sabes que mais ? Tudo bem ", "line 441": "Não ", "line 442": "Eu sei exatamente o que todos pensam de mim ", "line 443": "Não sou só alcoólica, também sou viciada em comprimidos ", "line 444": "É isso mesmo ", "line 445": "E metade de vocês compraram-mos ", "line 446": "Meu Deus ", "line 447": "Não se finjam de inocentes ", "line 448": "São uns hipócritas ! Todos ! Uns hipócritas ! Nona, estou a vê la ", "line 449": "Eu dei o meu coração a esta comunidade ", "line 450": "E sinto me um pouco magoada por me deixarem a a margem, mas paguei por os meus pecados ", "line 451": "E tenho uma vida que vai muito para além de Bailey Downs ", "line 452": "Eu faço parte de uma irmandade que vocês são incapazes de entender ", "line 453": "E graças a Deus nunca entenderão ", "line 454": "Onde vais ? Vou mijar ", "line 455": "Aqueces me o lugar ? - Olá, Art ", "line 456": "- O que raio se passa ? Nós lamentamos estares em esta posição ", "line 457": "\" Nós \" ", "line 458": "O problema é esse ", "line 459": "Já não te protejo só a ti ", "line 460": "Eu sei ", "line 461": "A Rachel não pode saber o que está ali ", "line 462": "- Tu tens de empatá los ", "line 463": "- Empatá los ? Nós já vamos quase em a China ", "line 464": "Quem é que está ali ? O Duko ? Não, a ", "line 465": "livrou se de o corpo ", "line 466": "Achas que o enterraria em a garagem de os Hendrix ? Então quem é ? Sarah, eu estou perdido ", "line 467": "Eu tenho de saber ", "line 468": "É mau, mas não para ti, entendes ? É o ", "line 469": "Leekie ", "line 470": "O Donnie matou o ", "line 471": "E o Art, Sarah ? Ele não tem uma opção ? Ele está tão envolvido como tu, Alison ", "line 472": "A culpa é minha ", "line 473": "Fui eu que matei o ", "line 474": "Lee ", "line 475": "Leekie ", "line 476": "Sarah, o que é que a Rachel vai fazer quando descobrir o Leekie decapitado ? - Vem atrás de nós todos ", "line 477": "- Está bem ", "line 478": "Eu digo lhes ", "line 479": "- Dizes o quê ? - Onde está a Helena ", "line 480": "Tu sabes desde o início ? Ela obrigou me a jurar que não dizia a ninguém a não ser a a Sarah ", "line 481": "- Não, não ", "line 482": "Nós não vamos dizer onde está a Helena ", "line 483": "- Não, claro que não ", "line 484": "- Desculpem ", "line 485": "- Não sei como salvar nos de esta ", "line 486": "- Tudo bem ", "line 487": "É de a nossa responsabilidade ", "line 488": "A Rachel deve saber ", "line 489": "Podes levá lo para casa, por favor ? - Sim ", "line 490": "O que vais fazer ? - Para variar, vou tornar me útil ", "line 491": "Sim ? - Alison Hendrix está aqui ", "line 492": "- Bom trabalho, ", "line 493": "Frontenac ", "line 494": "Encontrei a coisa mole ", "line 495": "Alison Hendrix ", "line 496": "Finalmente conhecemo nos ", "line 497": "Sim ", "line 498": "Acho que toda a minha vida está arquivada aqui algures ", "line 499": "Está ", "line 500": "Não que lhe tenha dado muita atenção ", "line 501": "Sei que me subestimas, Rachel ", "line 502": "Deves perguntar te porque é que as minhas irmãs se preocupam com mim ", "line 503": "Mas estou em esta guerra desde o princípio, com a Beth ", "line 504": "Ainda antes de a Sarah ", "line 505": "E estou para ficar ", "line 506": "Parece que em os falta qualquer coisa ", "line 507": "Foi um acidente ", "line 508": "O Dr ", "line 509": "Leekie levou o Donnie a o limite e ele não tinha formação básica em segurança com armas ", "line 510": "Aldous Leekie está enterrado em a tua garagem ? Menos a cabeça que foi doada a a Ciência ", "line 511": "Durante grande parte de a minha vida eu odiei o Aldous, mas escolhi não matá lo ", "line 512": "- O outro corpo ", "line 513": "Quem é ? - Um Castor ", "line 514": "Diz me onde está a Helena e tudo isto desaparece ", "line 515": "Mesmo que soubesse onde ela está, não te dizia ", "line 516": "Isto não é um problema nosso, é teu ", "line 517": "Por isso, força, acusa nos de homicídio ", "line 518": "Tudo vai dar a ti e a o teu gabinete ", "line 519": "Achas mesmo que o teu novo chefe quer tanta atenção sobre a Neo-evolução ? Toma ", "line 520": "Tira os de a minha casa ", "line 521": "Tira os de a minha casa ! - Enger ", "line 522": "- É a Rachel ", "line 523": "Surgiu uma coisa de o meu lado ", "line 524": "Preciso de saber o que encontrou, inspetora ", "line 525": "Há aqui um corpo, mas não conseguimos identificá lo ", "line 526": "O que quer que façamos ? Desfaçam se de os corpos discretamente e arrumem a garagem ", "line 527": "Muito bem ", "line 528": "Vamos retirar ", "line 529": "Parece que os Hendrixes se livraram de esta ", "line 530": "O que queres que faça contigo agora ? Faz o que quiseres com mim, mas deixa a Helena em paz ", "line 531": "Eu gostava de pôr as mãos em o teu pescoço e apertar ", "line 532": "Então não somos assim tão diferentes ", "line 533": "Tu conseguiste, querida ", "line 534": "Tu fizeste frente a a Rachel Duncan e não revelaste o esconderijo de a Helena ", "line 535": "O que é que se passa ? Sinto que tenho andado a as voltas em a minha própria pele há algum tempo ", "line 536": "E acho que finalmente me libertei ", "line 537": "Preciso de me afastar durante algum tempo ", "line 538": "Tu és o meu apoio ", "line 539": "Não me vou embora ", "line 540": "Eu só ", "line 541": "Eu preciso de ver os miúdos e ver quem sou fora de tudo isto ", "line 542": "- Uma espécie de retiro de ioga ? - Não, não sei para onde vou ", "line 543": "- Só preciso ", "line 544": "Sei que isto está certo ", "line 545": "- Sim ", "line 546": "Sei que há uma coisa que queres, meu homem de as Terras Altas ", "line 547": "A sério ? Queres fazer isto ? Não há montanha alta Não há vale profundo Não há rio largo o suficiente Se precisares, chama Estejas onde estiveres Por mais longe Não te preocupes, querida Chama o meu nome Estarei lá "}